{"id": 404930, "media_id": "2233156", "title": {"english": "(SPARK14) [JAPAN (usa)] Hataraku Sugimoto-san  (Golden Kamuy) [Chinese]", "japanese": "(SPARK14) [JAPAN (usa)] 働く杉元さん (ゴールデンカムイ) [中国翻訳]", "pretty": "Hataraku Sugimoto-san"}, "images": {"pages": [{"t": "j", "w": 900, "h": 1268}, {"t": "j", "w": 900, "h": 1281}, {"t": "j", "w": 900, "h": 1282}, {"t": "j", "w": 900, "h": 1283}, {"t": "j", "w": 900, "h": 1279}, {"t": "j", "w": 900, "h": 1280}, {"t": "j", "w": 900, "h": 1279}, {"t": "j", "w": 900, "h": 1280}, {"t": "j", "w": 900, "h": 1280}, {"t": "j", "w": 900, "h": 1280}, {"t": "j", "w": 900, "h": 1281}, {"t": "j", "w": 900, "h": 1279}, {"t": "j", "w": 900, "h": 1278}, {"t": "j", "w": 900, "h": 1279}, {"t": "j", "w": 900, "h": 1281}, {"t": "j", "w": 900, "h": 1281}, {"t": "j", "w": 900, "h": 1279}, {"t": "j", "w": 900, "h": 1278}, {"t": "j", "w": 900, "h": 1278}, {"t": "j", "w": 900, "h": 1280}, {"t": "j", "w": 900, "h": 1279}, {"t": "j", "w": 900, "h": 1280}, {"t": "j", "w": 900, "h": 1279}, {"t": "j", "w": 900, "h": 1274}, {"t": "j", "w": 900, "h": 1278}, {"t": "j", "w": 900, "h": 1281}, {"t": "j", "w": 900, "h": 1282}], "cover": {"t": "j", "w": 350, "h": 493}, "thumbnail": {"t": "j", "w": 250, "h": 352}}, "scanlator": "", "upload_date": 1653872109, "tags": [{"id": 12695, "type": "tag", "name": "prostitution", "url": "/tag/prostitution/", "count": 8005}, {"id": 13989, "type": "tag", "name": "ahegao", "url": "/tag/ahegao/", "count": 38276}, {"id": 14283, "type": "tag", "name": "anal", "url": "/tag/anal/", "count": 83683}, {"id": 14971, "type": "tag", "name": "sex toys", "url": "/tag/sex-toys/", "count": 26923}, {"id": 17249, "type": "language", "name": "translated", "url": "/language/translated/", "count": 162767}, {"id": 19018, "type": "tag", "name": "dark skin", "url": "/tag/dark-skin/", "count": 29408}, {"id": 19616, "type": "artist", "name": "usa", "url": "/artist/usa/", "count": 24}, {"id": 20362, "type": "tag", "name": "gyaru-oh", "url": "/tag/gyaru-oh/", "count": 1524}, {"id": 21712, "type": "tag", "name": "males only", "url": "/tag/males-only/", "count": 32719}, {"id": 23895, "type": "tag", "name": "yaoi", "url": "/tag/yaoi/", "count": 39572}, {"id": 29859, "type": "tag", "name": "blowjob", "url": "/tag/blowjob/", "count": 55737}, {"id": 29963, "type": "language", "name": "chinese", "url": "/language/chinese/", "count": 75593}, {"id": 30473, "type": "tag", "name": "muscle", "url": "/tag/muscle/", "count": 14371}, {"id": 33172, "type": "category", "name": "doujinshi", "url": "/category/doujinshi/", "count": 302852}, {"id": 90112, "type": "parody", "name": "golden kamuy", "url": "/parody/golden-kamuy/", "count": 74}, {"id": 90114, "type": "character", "name": "saichi sugimoto", "url": "/character/saichi-sugimoto/", "count": 41}, {"id": 111347, "type": "group", "name": "japan", "url": "/group/japan/", "count": 10}, {"id": 130025, "type": "tag", "name": "anal intercourse", "url": "/tag/anal-intercourse/", "count": 5164}], "num_pages": 27, "num_favorites": 485}