{"id": 415441, "media_id": "2300720", "title": {"english": "[Takemasaya (Takemasa Takeshi)] JK to Hajimete Ecchi - First Sex With JK (THE iDOLM@STER CINDERELLA GIRLS) [Digital]", "japanese": "[たけまさ屋 (武将武)] JKとはじめてえっち♥ (アイドルマスター シンデレラガールズ) [DL版]", "pretty": "JK to Hajimete Ecchi - First Sex With JK"}, "images": {"pages": [{"t": "j", "w": 1280, "h": 1813}, {"t": "j", "w": 1280, "h": 1790}, {"t": "j", "w": 1280, "h": 1790}, {"t": "j", "w": 1280, "h": 1790}, {"t": "j", "w": 1280, "h": 1790}, {"t": "j", "w": 1280, "h": 1790}, {"t": "j", "w": 1280, "h": 1790}, {"t": "j", "w": 1280, "h": 1790}, {"t": "j", "w": 1280, "h": 1790}, {"t": "j", "w": 1280, "h": 1790}, {"t": "j", "w": 1280, "h": 1790}, {"t": "j", "w": 1280, "h": 1790}, {"t": "j", "w": 1280, "h": 1790}, {"t": "j", "w": 1280, "h": 1790}, {"t": "j", "w": 1280, "h": 1790}, {"t": "j", "w": 1280, "h": 1790}, {"t": "j", "w": 1280, "h": 1790}, {"t": "j", "w": 1280, "h": 1790}, {"t": "j", "w": 1280, "h": 1790}, {"t": "j", "w": 1280, "h": 1790}, {"t": "j", "w": 1280, "h": 1790}, {"t": "j", "w": 1280, "h": 1790}, {"t": "j", "w": 1280, "h": 1790}, {"t": "j", "w": 1280, "h": 1790}, {"t": "j", "w": 1280, "h": 1790}, {"t": "j", "w": 1280, "h": 1790}, {"t": "j", "w": 1280, "h": 1790}, {"t": "j", "w": 1280, "h": 1790}, {"t": "j", "w": 1280, "h": 1790}, {"t": "j", "w": 1280, "h": 1790}, {"t": "j", "w": 1280, "h": 1790}, {"t": "j", "w": 1280, "h": 1790}, {"t": "j", "w": 1280, "h": 1790}, {"t": "j", "w": 1280, "h": 1790}, {"t": "j", "w": 1280, "h": 1790}, {"t": "j", "w": 1280, "h": 1790}, {"t": "j", "w": 1280, "h": 1790}, {"t": "j", "w": 1280, "h": 1790}, {"t": "j", "w": 1280, "h": 1790}, {"t": "j", "w": 1280, "h": 1790}, {"t": "j", "w": 1280, "h": 1790}, {"t": "j", "w": 1280, "h": 1790}, {"t": "j", "w": 1280, "h": 1790}, {"t": "j", "w": 1280, "h": 1790}, {"t": "j", "w": 1280, "h": 1790}, {"t": "j", "w": 1280, "h": 1813}], "cover": {"t": "j", "w": 350, "h": 496}, "thumbnail": {"t": "j", "w": 250, "h": 354}}, "scanlator": "", "upload_date": 1660628180, "tags": [{"id": 6346, "type": "language", "name": "japanese", "url": "/language/japanese/", "count": 232455}, {"id": 9754, "type": "group", "name": "takemasaya", "url": "/group/takemasaya/", "count": 76}, {"id": 10127, "type": "character", "name": "karen hojo", "url": "/character/karen-hojo/", "count": 104}, {"id": 12170, "type": "artist", "name": "takemasa takeshi", "url": "/artist/takemasa-takeshi/", "count": 98}, {"id": 20925, "type": "parody", "name": "the idolmaster", "url": "/parody/the-idolmaster/", "count": 11546}, {"id": 33172, "type": "category", "name": "doujinshi", "url": "/category/doujinshi/", "count": 302433}, {"id": 69904, "type": "character", "name": "sae kobayakawa", "url": "/character/sae-kobayakawa/", "count": 65}, {"id": 85295, "type": "tag", "name": "twintails", "url": "/tag/twintails/", "count": 17741}, {"id": 124874, "type": "character", "name": "yui ohtsuki", "url": "/character/yui-ohtsuki/", "count": 31}], "num_pages": 46, "num_favorites": 0}