{"id": "432815", "media_id": "2409492", "title": {"english": "(C100) [Nami-Nami Restaurant (Tsukinami Kousuke)] Unryuu ni Omakasekudasai (Kantai Collection -KanColle-)", "japanese": "(C100) [並々食堂 (月並甲介)] 雲龍にお任せ下さい (艦隊これくしょん -艦これ-)", "pretty": "Unryuu ni Omakasekudasai"}, "images": {"pages": [{"t": "j", "w": 1280, "h": 1863}, {"t": "j", "w": 1280, "h": 1868}, {"t": "j", "w": 1280, "h": 1867}, {"t": "j", "w": 1280, "h": 1867}, {"t": "j", "w": 1280, "h": 1861}, {"t": "j", "w": 1280, "h": 1857}, {"t": "j", "w": 1280, "h": 1859}, {"t": "j", "w": 1280, "h": 1867}, {"t": "j", "w": 1280, "h": 1865}, {"t": "j", "w": 1280, "h": 1866}, {"t": "j", "w": 1280, "h": 1864}, {"t": "j", "w": 1280, "h": 1863}, {"t": "j", "w": 1280, "h": 1865}, {"t": "j", "w": 1280, "h": 1865}, {"t": "j", "w": 1280, "h": 1863}, {"t": "j", "w": 1280, "h": 1865}, {"t": "j", "w": 1280, "h": 1867}, {"t": "j", "w": 1280, "h": 1867}, {"t": "j", "w": 1280, "h": 1869}, {"t": "j", "w": 1280, "h": 1867}, {"t": "j", "w": 1280, "h": 1874}], "cover": {"t": "j", "w": 350, "h": 510}, "thumbnail": {"t": "j", "w": 250, "h": 364}}, "scanlator": "", "upload_date": 1671718105, "tags": [{"id": 1841, "type": "parody", "name": "kantai collection", "url": "/parody/kantai-collection/", "count": 16908}, {"id": 29922, "type": "character", "name": "teitoku", "url": "/character/teitoku/", "count": 9328}, {"id": 6116, "type": "character", "name": "unryuu", "url": "/character/unryuu/", "count": 76}, {"id": 16690, "type": "group", "name": "nami-nami restaurant", "url": "/group/nami-nami-restaurant/", "count": 15}, {"id": 14598, "type": "artist", "name": "tsukinami kousuke", "url": "/artist/tsukinami-kousuke/", "count": 24}, {"id": 1033, "type": "tag", "name": "handjob", "url": "/tag/handjob/", "count": 9790}, {"id": 35762, "type": "tag", "name": "sole female", "url": "/tag/sole-female/", "count": 112686}, {"id": 8368, "type": "tag", "name": "full censorship", "url": "/tag/full-censorship/", "count": 23758}, {"id": 33172, "type": "category", "name": "doujinshi", "url": "/category/doujinshi/", "count": 321547}, {"id": 6346, "type": "language", "name": "japanese", "url": "/language/japanese/", "count": 243379}, {"id": 35763, "type": "tag", "name": "sole male", "url": "/tag/sole-male/", "count": 100079}], "num_pages": 21, "num_favorites": 1244}