{"id": 448187, "media_id": "2506189", "title": {"english": "[Goma Gorilla] Kanao to Aoi Hen (Kimetsu no Yaiba) [Ongoing]", "japanese": "[ごまゴリラ] カナヲとアオイ編 (鬼滅の刃) [進行中]", "pretty": "Kanao to Aoi Hen"}, "images": {"pages": [{"t": "j", "w": 965, "h": 1364}, {"t": "j", "w": 964, "h": 1364}, {"t": "j", "w": 965, "h": 1364}, {"t": "j", "w": 965, "h": 1364}, {"t": "j", "w": 1280, "h": 1810}, {"t": "j", "w": 965, "h": 1364}, {"t": "j", "w": 965, "h": 1364}, {"t": "j", "w": 965, "h": 1364}, {"t": "j", "w": 965, "h": 1364}, {"t": "j", "w": 965, "h": 1364}, {"t": "j", "w": 965, "h": 1364}, {"t": "j", "w": 965, "h": 1364}, {"t": "j", "w": 965, "h": 1364}, {"t": "j", "w": 965, "h": 1364}, {"t": "j", "w": 965, "h": 1364}, {"t": "j", "w": 965, "h": 1364}, {"t": "j", "w": 965, "h": 1364}, {"t": "j", "w": 965, "h": 1364}, {"t": "j", "w": 965, "h": 1364}, {"t": "j", "w": 965, "h": 1364}, {"t": "j", "w": 965, "h": 1364}, {"t": "j", "w": 965, "h": 1364}, {"t": "j", "w": 965, "h": 1364}, {"t": "j", "w": 965, "h": 1364}, {"t": "j", "w": 965, "h": 1364}, {"t": "j", "w": 965, "h": 1364}], "cover": {"t": "j", "w": 350, "h": 494}, "thumbnail": {"t": "j", "w": 250, "h": 354}}, "scanlator": "", "upload_date": 1680011951, "tags": [{"id": 1037, "type": "tag", "name": "oni", "url": "/tag/oni/", "count": 2642}, {"id": 2937, "type": "tag", "name": "big breasts", "url": "/tag/big-breasts/", "count": 151272}, {"id": 2956, "type": "tag", "name": "old man", "url": "/tag/old-man/", "count": 3565}, {"id": 6346, "type": "language", "name": "japanese", "url": "/language/japanese/", "count": 252800}, {"id": 13989, "type": "tag", "name": "ahegao", "url": "/tag/ahegao/", "count": 41738}, {"id": 14283, "type": "tag", "name": "anal", "url": "/tag/anal/", "count": 91486}, {"id": 20035, "type": "tag", "name": "x-ray", "url": "/tag/x-ray/", "count": 31247}, {"id": 21572, "type": "tag", "name": "multi-work series", "url": "/tag/multi-work-series/", "count": 30508}, {"id": 24676, "type": "tag", "name": "rimjob", "url": "/tag/rimjob/", "count": 6241}, {"id": 27553, "type": "tag", "name": "rape", "url": "/tag/rape/", "count": 47830}, {"id": 29013, "type": "tag", "name": "dilf", "url": "/tag/dilf/", "count": 22940}, {"id": 32484, "type": "tag", "name": "stomach deformation", "url": "/tag/stomach-deformation/", "count": 7637}, {"id": 33172, "type": "category", "name": "doujinshi", "url": "/category/doujinshi/", "count": 337869}, {"id": 73750, "type": "tag", "name": "bald", "url": "/tag/bald/", "count": 5917}, {"id": 79467, "type": "parody", "name": "kimetsu no yaiba", "url": "/parody/kimetsu-no-yaiba/", "count": 643}, {"id": 85288, "type": "tag", "name": "ponytail", "url": "/tag/ponytail/", "count": 21193}, {"id": 85295, "type": "tag", "name": "twintails", "url": "/tag/twintails/", "count": 22002}, {"id": 88846, "type": "tag", "name": "horns", "url": "/tag/horns/", "count": 6643}, {"id": 114694, "type": "character", "name": "kanao tsuyuri", "url": "/character/kanao-tsuyuri/", "count": 63}, {"id": 117272, "type": "character", "name": "aoi kanzaki", "url": "/character/aoi-kanzaki/", "count": 32}, {"id": 143476, "type": "artist", "name": "goma gorilla", "url": "/artist/goma-gorilla/", "count": 34}], "num_pages": 26, "num_favorites": 556}