{"id": 452326, "media_id": "2533407", "title": {"english": "[Permission (Kanashiro no Hako)] Chuuka Succubus no Ikoku Esthe ni Goyoujin ~Succubus no Onee-san ni Damasare Muriyari Nurunuru Ochinchin o Shiborarechau Ohanashi~ [Chinese] [白杨汉化组]", "japanese": "[ぱ～みっしょん (かなしろの箱)] 中華サキュバスの異国エステにご用心～サキュバスのお姉さんに騙され無理矢理ヌルヌルオチン〇ンを搾られちゃうお話～ [中国翻訳]", "pretty": "Chuuka Succubus no Ikoku Esthe ni Goyoujin"}, "images": {"pages": [{"t": "j", "w": 1120, "h": 840}, {"t": "j", "w": 1240, "h": 1754}, {"t": "j", "w": 1240, "h": 1754}, {"t": "j", "w": 1240, "h": 1754}, {"t": "j", "w": 1240, "h": 1754}, {"t": "j", "w": 1240, "h": 1754}, {"t": "j", "w": 1240, "h": 1754}, {"t": "j", "w": 1240, "h": 1754}, {"t": "j", "w": 1240, "h": 1754}, {"t": "j", "w": 1240, "h": 1754}, {"t": "j", "w": 1240, "h": 1754}, {"t": "j", "w": 1240, "h": 1754}, {"t": "j", "w": 1240, "h": 1754}, {"t": "j", "w": 1240, "h": 1754}, {"t": "j", "w": 1240, "h": 1754}, {"t": "j", "w": 1240, "h": 1754}, {"t": "j", "w": 1240, "h": 1754}, {"t": "j", "w": 1240, "h": 1754}, {"t": "j", "w": 1240, "h": 1754}, {"t": "j", "w": 1240, "h": 1754}, {"t": "j", "w": 1240, "h": 1754}, {"t": "j", "w": 1240, "h": 1754}, {"t": "j", "w": 1240, "h": 1754}, {"t": "j", "w": 1240, "h": 1754}, {"t": "j", "w": 888, "h": 1219}, {"t": "j", "w": 1280, "h": 2440}], "cover": {"t": "j", "w": 350, "h": 262}, "thumbnail": {"t": "j", "w": 250, "h": 188}}, "scanlator": "", "upload_date": 1682413008, "tags": [{"id": 2153, "type": "tag", "name": "wings", "url": "/tag/wings/", "count": 3277}, {"id": 15408, "type": "tag", "name": "femdom", "url": "/tag/femdom/", "count": 24121}, {"id": 16228, "type": "tag", "name": "demon girl", "url": "/tag/demon-girl/", "count": 8526}, {"id": 17249, "type": "language", "name": "translated", "url": "/language/translated/", "count": 180282}, {"id": 24450, "type": "tag", "name": "chinese dress", "url": "/tag/chinese-dress/", "count": 1309}, {"id": 29963, "type": "language", "name": "chinese", "url": "/language/chinese/", "count": 87309}, {"id": 32341, "type": "tag", "name": "shotacon", "url": "/tag/shotacon/", "count": 52208}, {"id": 33172, "type": "category", "name": "doujinshi", "url": "/category/doujinshi/", "count": 331412}, {"id": 35762, "type": "tag", "name": "sole female", "url": "/tag/sole-female/", "count": 117882}, {"id": 35763, "type": "tag", "name": "sole male", "url": "/tag/sole-male/", "count": 104374}, {"id": 73376, "type": "group", "name": "permission", "url": "/group/permission/", "count": 12}, {"id": 88846, "type": "tag", "name": "horns", "url": "/tag/horns/", "count": 6312}, {"id": 90671, "type": "parody", "name": "original", "url": "/parody/original/", "count": 63135}, {"id": 104227, "type": "tag", "name": "tail", "url": "/tag/tail/", "count": 6216}, {"id": 106733, "type": "tag", "name": "hair buns", "url": "/tag/hair-buns/", "count": 2665}], "num_pages": 26, "num_favorites": 0}