{"id": 494193, "media_id": "2814582", "title": {"english": "[Ebiken Sanchi (Ebiken?!))] Senzoku!! Hatsujouki Shorikei (Hololive)", "japanese": "[エビケンさんち (エビケン?!)] せんぞく!!発情期処理係 (ホロライブ)", "pretty": "Senzoku!! Hatsujouki Shorikei"}, "images": {"pages": [{"t": "j", "w": 1280, "h": 1780}, {"t": "j", "w": 1280, "h": 1780}, {"t": "j", "w": 1280, "h": 1780}, {"t": "j", "w": 1280, "h": 1780}, {"t": "j", "w": 1280, "h": 1780}, {"t": "j", "w": 1280, "h": 1780}, {"t": "j", "w": 1280, "h": 1780}, {"t": "j", "w": 1280, "h": 1780}, {"t": "j", "w": 1280, "h": 1780}, {"t": "j", "w": 1280, "h": 1780}, {"t": "j", "w": 1280, "h": 1780}, {"t": "j", "w": 1280, "h": 1780}, {"t": "j", "w": 1280, "h": 1780}, {"t": "j", "w": 1280, "h": 1780}, {"t": "j", "w": 1280, "h": 1780}, {"t": "j", "w": 1280, "h": 1780}, {"t": "j", "w": 1280, "h": 1780}, {"t": "j", "w": 1280, "h": 1780}, {"t": "j", "w": 1280, "h": 1780}, {"t": "j", "w": 1280, "h": 1780}, {"t": "j", "w": 1280, "h": 1780}, {"t": "j", "w": 1280, "h": 1780}, {"t": "j", "w": 1280, "h": 1780}, {"t": "j", "w": 1280, "h": 1780}], "cover": {"t": "j", "w": 350, "h": 486}, "thumbnail": {"t": "j", "w": 250, "h": 348}}, "scanlator": "", "upload_date": 1706692327, "tags": [{"id": 2937, "type": "tag", "name": "big breasts", "url": "/tag/big-breasts/", "count": 164244}, {"id": 6346, "type": "language", "name": "japanese", "url": "/language/japanese/", "count": 268424}, {"id": 8010, "type": "tag", "name": "group", "url": "/tag/group/", "count": 102034}, {"id": 12824, "type": "tag", "name": "condom", "url": "/tag/condom/", "count": 11708}, {"id": 13720, "type": "tag", "name": "nakadashi", "url": "/tag/nakadashi/", "count": 78543}, {"id": 13989, "type": "tag", "name": "ahegao", "url": "/tag/ahegao/", "count": 44982}, {"id": 14283, "type": "tag", "name": "anal", "url": "/tag/anal/", "count": 97280}, {"id": 14516, "type": "tag", "name": "wolf girl", "url": "/tag/wolf-girl/", "count": 1318}, {"id": 15119, "type": "tag", "name": "dog girl", "url": "/tag/dog-girl/", "count": 1579}, {"id": 15348, "type": "tag", "name": "ffm threesome", "url": "/tag/ffm-threesome/", "count": 28424}, {"id": 15785, "type": "tag", "name": "harem", "url": "/tag/harem/", "count": 12368}, {"id": 20035, "type": "tag", "name": "x-ray", "url": "/tag/x-ray/", "count": 34746}, {"id": 25766, "type": "tag", "name": "gokkun", "url": "/tag/gokkun/", "count": 2707}, {"id": 31285, "type": "tag", "name": "fox girl", "url": "/tag/fox-girl/", "count": 3940}, {"id": 31386, "type": "tag", "name": "catgirl", "url": "/tag/catgirl/", "count": 10921}, {"id": 33172, "type": "category", "name": "doujinshi", "url": "/category/doujinshi/", "count": 364211}, {"id": 81774, "type": "tag", "name": "kemonomimi", "url": "/tag/kemonomimi/", "count": 17634}, {"id": 104227, "type": "tag", "name": "tail", "url": "/tag/tail/", "count": 7891}, {"id": 104893, "type": "tag", "name": "vtuber", "url": "/tag/vtuber/", "count": 2209}, {"id": 116046, "type": "character", "name": "ookami mio", "url": "/character/ookami-mio/", "count": 45}, {"id": 124349, "type": "character", "name": "shirakami fubuki", "url": "/character/shirakami-fubuki/", "count": 63}, {"id": 127065, "type": "parody", "name": "hololive", "url": "/parody/hololive/", "count": 1031}, {"id": 128276, "type": "character", "name": "inugami korone", "url": "/character/inugami-korone/", "count": 27}, {"id": 128277, "type": "character", "name": "nekomata okayu", "url": "/character/nekomata-okayu/", "count": 88}, {"id": 151469, "type": "artist", "name": "ebiken", "url": "/artist/ebiken/", "count": 2}], "num_pages": 24, "num_favorites": 0}