{"id": 495790, "media_id": "2824728", "title": {"english": "[666PROTECT (Jingrock)] Musume no Tomodachi ga Yuuwaku Suru 2 [Digital]", "japanese": "[666PROTECT (甚六)] 娘のトモダチが誘惑する2 [DL版]", "pretty": "Musume no Tomodachi ga Yuuwaku Suru 2"}, "images": {"pages": [{"t": "j", "w": 1280, "h": 1533}, {"t": "j", "w": 1144, "h": 1600}, {"t": "j", "w": 1144, "h": 1600}, {"t": "j", "w": 1144, "h": 1600}, {"t": "j", "w": 1144, "h": 1600}, {"t": "j", "w": 1144, "h": 1600}, {"t": "j", "w": 1144, "h": 1600}, {"t": "j", "w": 1144, "h": 1600}, {"t": "j", "w": 1144, "h": 1600}, {"t": "j", "w": 1144, "h": 1600}, {"t": "j", "w": 1144, "h": 1600}, {"t": "j", "w": 1144, "h": 1600}, {"t": "j", "w": 1144, "h": 1600}, {"t": "j", "w": 1144, "h": 1600}, {"t": "j", "w": 1144, "h": 1600}, {"t": "j", "w": 1144, "h": 1600}, {"t": "j", "w": 1144, "h": 1600}, {"t": "j", "w": 1144, "h": 1600}, {"t": "j", "w": 1144, "h": 1600}, {"t": "j", "w": 1144, "h": 1600}, {"t": "j", "w": 1144, "h": 1600}, {"t": "j", "w": 1144, "h": 1600}, {"t": "j", "w": 1144, "h": 1600}, {"t": "j", "w": 1144, "h": 1600}, {"t": "j", "w": 1144, "h": 1600}, {"t": "j", "w": 1144, "h": 1600}, {"t": "j", "w": 1144, "h": 1600}, {"t": "j", "w": 1144, "h": 1600}, {"t": "j", "w": 1144, "h": 1600}, {"t": "j", "w": 1144, "h": 1600}, {"t": "j", "w": 1144, "h": 1600}, {"t": "j", "w": 1144, "h": 1600}, {"t": "j", "w": 1144, "h": 1600}, {"t": "j", "w": 1144, "h": 1600}, {"t": "j", "w": 1144, "h": 1600}, {"t": "j", "w": 1144, "h": 1600}, {"t": "j", "w": 1144, "h": 1600}], "cover": {"t": "j", "w": 350, "h": 419}, "thumbnail": {"t": "j", "w": 250, "h": 300}}, "scanlator": "", "upload_date": 1707574121, "tags": [{"id": 90671, "type": "parody", "name": "original", "url": "/parody/original/", "count": 76721}, {"id": 13937, "type": "group", "name": "666protect", "url": "/group/666protect/", "count": 2}, {"id": 18930, "type": "artist", "name": "jingrock", "url": "/artist/jingrock/", "count": 2}, {"id": 31880, "type": "tag", "name": "bbm", "url": "/tag/bbm/", "count": 18570}, {"id": 29013, "type": "tag", "name": "dilf", "url": "/tag/dilf/", "count": 23317}, {"id": 8378, "type": "tag", "name": "glasses", "url": "/tag/glasses/", "count": 63480}, {"id": 2937, "type": "tag", "name": "big breasts", "url": "/tag/big-breasts/", "count": 156018}, {"id": 29859, "type": "tag", "name": "blowjob", "url": "/tag/blowjob/", "count": 68126}, {"id": 129668, "type": "tag", "name": "eye-covering bang", "url": "/tag/eye-covering-bang/", "count": 3013}, {"id": 1643, "type": "tag", "name": "kissing", "url": "/tag/kissing/", "count": 12605}, {"id": 13720, "type": "tag", "name": "nakadashi", "url": "/tag/nakadashi/", "count": 75120}, {"id": 35762, "type": "tag", "name": "sole female", "url": "/tag/sole-female/", "count": 132190}, {"id": 21572, "type": "tag", "name": "multi-work series", "url": "/tag/multi-work-series/", "count": 33454}, {"id": 33172, "type": "category", "name": "doujinshi", "url": "/category/doujinshi/", "count": 357921}, {"id": 6346, "type": "language", "name": "japanese", "url": "/language/japanese/", "count": 262925}, {"id": 35763, "type": "tag", "name": "sole male", "url": "/tag/sole-male/", "count": 117177}, {"id": 15408, "type": "tag", "name": "femdom", "url": "/tag/femdom/", "count": 24826}], "num_pages": 37, "num_favorites": 3384}