{"result": [{"id": 471574, "media_id": "2664273", "title": {"english": "[Itaba Hiroshi] Tsukiyono Kachou wa Gal o Yamerarenai  - Tsukiyono The manager can't quit a gal [Digital]", "japanese": "[板場広し] 月夜野課長はギャルをやめられない [DL版]", "pretty": "Tsukiyono Kachou wa Gal o Yamerarenai  - Tsukiyono The manager can't quit a gal"}, "images": {"pages": [{"t": "j", "w": 1057, "h": 1500}, {"t": "j", "w": 1042, "h": 1500}, {"t": "j", "w": 1057, "h": 1500}, {"t": "j", "w": 1057, "h": 1500}, {"t": "j", "w": 1057, "h": 1500}, {"t": "j", "w": 1057, "h": 1500}, {"t": "j", "w": 1057, "h": 1500}, {"t": "j", "w": 1057, "h": 1500}, {"t": "j", "w": 1057, "h": 1500}, {"t": "j", "w": 1057, "h": 1500}, {"t": "j", "w": 1057, "h": 1500}, {"t": "j", "w": 1057, "h": 1500}, {"t": "j", "w": 1057, "h": 1500}, {"t": "j", "w": 1057, "h": 1500}, {"t": "j", "w": 1057, "h": 1500}, {"t": "j", "w": 1057, "h": 1500}, {"t": "j", "w": 1057, "h": 1500}, {"t": "j", "w": 1057, "h": 1500}, {"t": "j", "w": 1057, "h": 1500}, {"t": "j", "w": 1057, "h": 1500}, {"t": "j", "w": 1057, "h": 1500}, {"t": "j", "w": 1057, "h": 1500}, {"t": "j", "w": 1057, "h": 1500}, {"t": "j", "w": 1057, "h": 1500}, {"t": "j", "w": 1057, "h": 1500}, {"t": "j", "w": 1057, "h": 1500}, {"t": "j", "w": 1057, "h": 1500}, {"t": "j", "w": 1057, "h": 1500}, {"t": "j", "w": 1057, "h": 1500}, {"t": "j", "w": 1057, "h": 1500}, {"t": "j", "w": 1057, "h": 1500}, {"t": "j", "w": 1057, "h": 1500}, {"t": "j", "w": 1057, "h": 1500}, {"t": "j", "w": 1057, "h": 1500}, {"t": "j", "w": 1057, "h": 1500}, {"t": "j", "w": 1057, "h": 1500}, {"t": "j", "w": 1057, "h": 1500}, {"t": "j", "w": 1057, "h": 1500}, {"t": "j", "w": 1057, "h": 1500}, {"t": "j", "w": 1057, "h": 1500}, {"t": "j", "w": 1057, "h": 1500}, {"t": "j", "w": 1057, "h": 1500}, {"t": "j", "w": 1057, "h": 1500}, {"t": "j", "w": 1057, "h": 1500}, {"t": "j", "w": 1057, "h": 1500}, {"t": "j", "w": 1057, "h": 1500}, {"t": "j", "w": 1057, "h": 1500}, {"t": "j", "w": 1057, "h": 1500}, {"t": "j", "w": 1057, "h": 1500}, {"t": "j", "w": 1057, "h": 1500}, {"t": "j", "w": 1057, "h": 1500}, {"t": "j", "w": 1057, "h": 1500}, {"t": "j", "w": 1057, "h": 1500}, {"t": "j", "w": 1057, "h": 1500}, {"t": "j", "w": 1057, "h": 1500}, {"t": "j", "w": 1057, "h": 1500}, {"t": "j", "w": 1057, "h": 1500}, {"t": "j", "w": 1057, "h": 1500}, {"t": "j", "w": 1057, "h": 1500}, {"t": "j", "w": 1057, "h": 1500}, {"t": "j", "w": 1057, "h": 1500}, {"t": "j", "w": 1057, "h": 1500}, {"t": "j", "w": 1057, "h": 1500}, {"t": "j", "w": 1057, "h": 1500}, {"t": "j", "w": 1057, "h": 1500}, {"t": "j", "w": 1057, "h": 1500}, {"t": "j", "w": 1057, "h": 1500}, {"t": "j", "w": 1057, "h": 1500}, {"t": "j", "w": 1057, "h": 1500}, {"t": "j", "w": 1057, "h": 1500}, {"t": "j", "w": 1057, "h": 1500}, {"t": "j", "w": 1057, "h": 1500}, {"t": "j", "w": 1057, "h": 1500}, {"t": "j", "w": 1057, "h": 1500}, {"t": "j", "w": 1057, "h": 1500}, {"t": "j", "w": 1057, "h": 1500}, {"t": "j", "w": 1057, "h": 1500}, {"t": "j", "w": 1057, "h": 1500}, {"t": "j", "w": 1057, "h": 1500}, {"t": "j", "w": 1057, "h": 1500}, {"t": "j", "w": 1057, "h": 1500}, {"t": "j", "w": 1057, "h": 1500}, {"t": "j", "w": 1057, "h": 1500}, {"t": "j", "w": 1057, "h": 1500}, {"t": "j", "w": 1057, "h": 1500}, {"t": "j", "w": 1057, "h": 1500}, {"t": "j", "w": 1057, "h": 1500}, {"t": "j", "w": 1057, "h": 1500}, {"t": "j", "w": 1057, "h": 1500}, {"t": "j", "w": 1057, "h": 1500}, {"t": "j", "w": 1057, "h": 1500}, {"t": "j", "w": 1057, "h": 1500}, {"t": "j", "w": 1057, "h": 1500}, {"t": "j", "w": 1057, "h": 1500}, {"t": "j", "w": 1057, "h": 1500}, {"t": "j", "w": 1057, "h": 1500}, {"t": "j", "w": 1057, "h": 1500}, {"t": "j", "w": 1057, "h": 1500}, {"t": "j", "w": 1057, "h": 1500}, {"t": "j", "w": 1057, "h": 1500}, {"t": "j", "w": 1057, "h": 1500}, {"t": "j", "w": 1057, "h": 1500}, {"t": "j", "w": 1057, "h": 1500}, {"t": "j", "w": 1057, "h": 1500}, {"t": "j", "w": 1057, "h": 1500}, {"t": "j", "w": 1057, "h": 1500}, {"t": "j", "w": 1057, "h": 1500}, {"t": "j", "w": 1057, "h": 1500}, {"t": "j", "w": 1057, "h": 1500}, {"t": "j", "w": 1057, "h": 1500}, {"t": "j", "w": 1057, "h": 1500}, {"t": "j", "w": 1057, "h": 1500}, {"t": "j", "w": 1057, "h": 1500}, {"t": "j", "w": 1057, "h": 1500}, {"t": "j", "w": 1057, "h": 1500}, {"t": "j", "w": 1057, "h": 1500}, {"t": "j", "w": 1057, "h": 1500}, {"t": "j", "w": 1057, "h": 1500}, {"t": "j", "w": 1057, "h": 1500}, {"t": "j", "w": 1057, "h": 1500}, {"t": "j", "w": 1057, "h": 1500}, {"t": "j", "w": 1057, "h": 1500}, {"t": "j", "w": 1057, "h": 1500}, {"t": "j", "w": 1057, "h": 1500}, {"t": "j", "w": 1057, "h": 1500}, {"t": "j", "w": 1057, "h": 1500}, {"t": "j", "w": 1057, "h": 1500}, {"t": "j", "w": 1057, "h": 1500}, {"t": "j", "w": 1057, "h": 1500}, {"t": "j", "w": 1057, "h": 1500}, {"t": "j", "w": 1057, "h": 1500}, {"t": "j", "w": 1057, "h": 1500}, {"t": "j", "w": 1057, "h": 1500}, {"t": "j", "w": 1057, "h": 1500}, {"t": "j", "w": 1057, "h": 1500}, {"t": "j", "w": 1057, "h": 1500}, {"t": "j", "w": 1057, "h": 1500}, {"t": "j", "w": 1057, "h": 1500}, {"t": "j", "w": 1057, "h": 1500}, {"t": "j", "w": 1057, "h": 1500}, {"t": "j", "w": 1057, "h": 1500}, {"t": "j", "w": 1057, "h": 1500}, {"t": "j", "w": 1057, "h": 1500}, {"t": "j", "w": 1057, "h": 1500}, {"t": "j", "w": 1057, "h": 1500}, {"t": "j", "w": 1057, "h": 1500}, {"t": "j", "w": 1057, "h": 1500}, {"t": "j", "w": 1057, "h": 1500}, {"t": "j", "w": 1057, "h": 1500}, {"t": "j", "w": 1057, "h": 1500}, {"t": "j", "w": 1057, "h": 1500}, {"t": "j", "w": 1057, "h": 1500}, {"t": "j", "w": 1057, "h": 1500}, {"t": "j", "w": 1057, "h": 1500}, {"t": "j", "w": 1057, "h": 1500}, {"t": "j", "w": 1057, "h": 1500}, {"t": "j", "w": 1057, "h": 1500}, {"t": "j", "w": 1057, "h": 1500}, {"t": "j", "w": 1057, "h": 1500}, {"t": "j", "w": 1057, "h": 1500}, {"t": "j", "w": 1057, "h": 1500}, {"t": "j", "w": 1057, "h": 1500}, {"t": "j", "w": 1057, "h": 1500}, {"t": "j", "w": 1057, "h": 1500}, {"t": "j", "w": 1057, "h": 1500}, {"t": "j", "w": 1057, "h": 1500}, {"t": "j", "w": 1057, "h": 1500}, {"t": "j", "w": 1057, "h": 1500}, {"t": "j", "w": 1057, "h": 1500}, {"t": "j", "w": 1057, "h": 1500}, {"t": "j", "w": 1057, "h": 1500}, {"t": "j", "w": 1057, "h": 1500}, {"t": "j", "w": 1057, "h": 1500}, {"t": "j", "w": 1057, "h": 1500}, {"t": "j", "w": 1057, "h": 1500}, {"t": "j", "w": 1057, "h": 1500}, {"t": "j", "w": 1057, "h": 1500}, {"t": "j", "w": 1057, "h": 1500}, {"t": "j", "w": 1057, "h": 1500}, {"t": "j", "w": 1057, "h": 1500}, {"t": "j", "w": 1057, "h": 1500}, {"t": "j", "w": 1057, "h": 1500}, {"t": "j", "w": 1057, "h": 1500}, {"t": "j", "w": 1057, "h": 1500}, {"t": "j", "w": 1057, "h": 1500}, {"t": "j", "w": 1057, "h": 1500}, {"t": "j", "w": 1057, "h": 1500}, {"t": "j", "w": 1057, "h": 1500}, {"t": "j", "w": 1057, "h": 1500}, {"t": "j", "w": 1057, "h": 1500}, {"t": "j", "w": 1057, "h": 1500}, {"t": "j", "w": 1057, "h": 1500}, {"t": "j", "w": 1057, "h": 1500}, {"t": "j", "w": 1057, "h": 1500}, {"t": "j", "w": 1057, "h": 1500}, {"t": "j", "w": 1057, "h": 1500}, {"t": "j", "w": 1057, "h": 1500}, {"t": "j", "w": 1057, "h": 1500}, {"t": "j", "w": 1057, "h": 1500}, {"t": "j", "w": 1057, "h": 1500}, {"t": "j", "w": 1057, "h": 1500}, {"t": "j", "w": 1057, "h": 1500}, {"t": "j", "w": 1057, "h": 1500}, {"t": "j", "w": 1057, "h": 1500}, {"t": "j", "w": 1057, "h": 1500}, {"t": "j", "w": 1057, "h": 1500}, {"t": "j", "w": 1057, "h": 1500}, {"t": "j", "w": 1057, "h": 1500}, {"t": "j", "w": 1057, "h": 1500}, {"t": "j", "w": 1057, "h": 1500}, {"t": "j", "w": 1057, "h": 1500}, {"t": "j", "w": 1057, "h": 1500}, {"t": "j", "w": 1057, "h": 1500}, {"t": "j", "w": 1057, "h": 1500}, {"t": "j", "w": 1057, "h": 1500}, {"t": "j", "w": 1057, "h": 1500}, {"t": "j", "w": 1057, "h": 1500}, {"t": "j", "w": 1057, "h": 1500}, {"t": "j", "w": 1057, "h": 1500}, {"t": "j", "w": 1057, "h": 1500}, {"t": "j", "w": 1057, "h": 1500}, {"t": "j", "w": 1057, "h": 1500}, {"t": "j", "w": 1057, "h": 1500}, {"t": "j", "w": 1057, "h": 1500}, {"t": "j", "w": 1057, "h": 1500}, {"t": "j", "w": 1057, "h": 1500}, {"t": "j", "w": 1057, "h": 1500}, {"t": "j", "w": 1057, "h": 1500}, {"t": "j", "w": 1057, "h": 1500}, {"t": "j", "w": 1057, "h": 1500}, {"t": "j", "w": 1057, "h": 1500}, {"t": "j", "w": 1057, "h": 1500}, {"t": "j", "w": 1057, "h": 1500}, {"t": "j", "w": 1057, "h": 1500}, {"t": "j", "w": 1057, "h": 1500}, {"t": "j", "w": 1057, "h": 1500}, {"t": "j", "w": 1057, "h": 1500}, {"t": "j", "w": 1057, "h": 1500}, {"t": "j", "w": 1057, "h": 1500}, {"t": "j", "w": 1057, "h": 1500}, {"t": "j", "w": 1057, "h": 1500}, {"t": "j", "w": 1057, "h": 1500}, {"t": "j", "w": 1057, "h": 1500}, {"t": "j", "w": 1057, "h": 1500}, {"t": "j", "w": 1057, "h": 1500}, {"t": "j", "w": 1057, "h": 1500}, {"t": "j", "w": 1057, "h": 1500}], "cover": {"t": "j", "w": 350, "h": 496}, "thumbnail": {"t": "j", "w": 250, "h": 355}}, "scanlator": "", "upload_date": 1693831569, "tags": [{"id": 370, "type": "tag", "name": "business suit", "url": "/tag/business-suit/", "count": 5279}, {"id": 2937, "type": "tag", "name": "big breasts", "url": "/tag/big-breasts/", "count": 159879}, {"id": 5820, "type": "tag", "name": "piercing", "url": "/tag/piercing/", "count": 9489}, {"id": 6346, "type": "language", "name": "japanese", "url": "/language/japanese/", "count": 263704}, {"id": 8010, "type": "tag", "name": "group", "url": "/tag/group/", "count": 100203}, {"id": 8378, "type": "tag", "name": "glasses", "url": "/tag/glasses/", "count": 66162}, {"id": 8739, "type": "tag", "name": "story arc", "url": "/tag/story-arc/", "count": 17639}, {"id": 14072, "type": "tag", "name": "huge breasts", "url": "/tag/huge-breasts/", "count": 12106}, {"id": 14283, "type": "tag", "name": "anal", "url": "/tag/anal/", "count": 95590}, {"id": 20035, "type": "tag", "name": "x-ray", "url": "/tag/x-ray/", "count": 33419}, {"id": 22945, "type": "tag", "name": "double penetration", "url": "/tag/double-penetration/", "count": 33069}, {"id": 23237, "type": "tag", "name": "tankoubon", "url": "/tag/tankoubon/", "count": 32251}, {"id": 23632, "type": "tag", "name": "big areolae", "url": "/tag/big-areolae/", "count": 6837}, {"id": 24201, "type": "tag", "name": "stockings", "url": "/tag/stockings/", "count": 92158}, {"id": 25050, "type": "tag", "name": "gyaru", "url": "/tag/gyaru/", "count": 7002}, {"id": 25871, "type": "tag", "name": "lingerie", "url": "/tag/lingerie/", "count": 12715}, {"id": 29859, "type": "tag", "name": "blowjob", "url": "/tag/blowjob/", "count": 68491}, {"id": 32511, "type": "artist", "name": "itaba hiroshi", "url": "/artist/itaba-hiroshi/", "count": 707}, {"id": 33173, "type": "category", "name": "manga", "url": "/category/manga/", "count": 113710}, {"id": 130025, "type": "tag", "name": "anal intercourse", "url": "/tag/anal-intercourse/", "count": 12411}], "num_pages": 247, "num_favorites": 2985}, {"id": 471573, "media_id": "2664269", "title": {"english": "[Ankoman] Lakshmi Bai, Goblin no Mure to Tatakau (FateGrand Order) [English] [hardcase8translates]", "japanese": "", "pretty": "Lakshmi Bai, Goblin no Mure to Tatakau"}, "images": {"pages": [{"t": "j", "w": 1280, "h": 1780}, {"t": "j", "w": 1280, "h": 1780}, {"t": "j", "w": 1280, "h": 1780}, {"t": "j", "w": 1280, "h": 1350}, {"t": "j", "w": 1280, "h": 631}], "cover": {"t": "j", "w": 350, "h": 486}, "thumbnail": {"t": "j", "w": 250, "h": 348}}, "scanlator": "", "upload_date": 1693829775, "tags": [{"id": 3614, "type": "tag", "name": "triple penetration", "url": "/tag/triple-penetration/", "count": 1961}, {"id": 6343, "type": "tag", "name": "pregnant", "url": "/tag/pregnant/", "count": 13882}, {"id": 7256, "type": "tag", "name": "mmf threesome", "url": "/tag/mmf-threesome/", "count": 15535}, {"id": 8010, "type": "tag", "name": "group", "url": "/tag/group/", "count": 100203}, {"id": 8400, "type": "tag", "name": "goblin", "url": "/tag/goblin/", "count": 921}, {"id": 10794, "type": "tag", "name": "breast feeding", "url": "/tag/breast-feeding/", "count": 3782}, {"id": 12227, "type": "language", "name": "english", "url": "/language/english/", "count": 109685}, {"id": 14283, "type": "tag", "name": "anal", "url": "/tag/anal/", "count": 95588}, {"id": 15225, "type": "tag", "name": "blowjob face", "url": "/tag/blowjob-face/", "count": 3029}, {"id": 15658, "type": "tag", "name": "bondage", "url": "/tag/bondage/", "count": 46740}, {"id": 17249, "type": "language", "name": "translated", "url": "/language/translated/", "count": 195366}, {"id": 18328, "type": "tag", "name": "thigh high boots", "url": "/tag/thigh-high-boots/", "count": 5345}, {"id": 19018, "type": "tag", "name": "dark skin", "url": "/tag/dark-skin/", "count": 35404}, {"id": 20035, "type": "tag", "name": "x-ray", "url": "/tag/x-ray/", "count": 33417}, {"id": 22945, "type": "tag", "name": "double penetration", "url": "/tag/double-penetration/", "count": 33070}, {"id": 24102, "type": "tag", "name": "lactation", "url": "/tag/lactation/", "count": 17235}, {"id": 27384, "type": "tag", "name": "mind break", "url": "/tag/mind-break/", "count": 17960}, {"id": 27553, "type": "tag", "name": "rape", "url": "/tag/rape/", "count": 49973}, {"id": 29224, "type": "tag", "name": "impregnation", "url": "/tag/impregnation/", "count": 24981}, {"id": 29859, "type": "tag", "name": "blowjob", "url": "/tag/blowjob/", "count": 68486}, {"id": 31044, "type": "tag", "name": "collar", "url": "/tag/collar/", "count": 23392}, {"id": 31846, "type": "tag", "name": "body writing", "url": "/tag/body-writing/", "count": 1739}, {"id": 33172, "type": "category", "name": "doujinshi", "url": "/category/doujinshi/", "count": 356214}, {"id": 35605, "type": "parody", "name": "fate grand order", "url": "/parody/fate-grand-order/", "count": 13767}, {"id": 35762, "type": "tag", "name": "sole female", "url": "/tag/sole-female/", "count": 131259}, {"id": 74016, "type": "artist", "name": "ankoman", "url": "/artist/ankoman/", "count": 645}, {"id": 101724, "type": "tag", "name": "leash", "url": "/tag/leash/", "count": 1794}, {"id": 116276, "type": "character", "name": "lakshmibai", "url": "/character/lakshmibai/", "count": 13}, {"id": 122908, "type": "tag", "name": "very long hair", "url": "/tag/very-long-hair/", "count": 4640}, {"id": 130025, "type": "tag", "name": "anal intercourse", "url": "/tag/anal-intercourse/", "count": 12411}, {"id": 140924, "type": "tag", "name": "smalldom", "url": "/tag/smalldom/", "count": 510}, {"id": 147760, "type": "tag", "name": "gang rape", "url": "/tag/gang-rape/", "count": 36}], "num_pages": 5, "num_favorites": 3548}, {"id": 471572, "media_id": "2664262", "title": {"english": "[Anthology] Futanari Friends! 20", "japanese": "[アンソロジー] ふたなりフレンズ！20", "pretty": "Futanari Friends! 20"}, "images": {"pages": [{"t": "j", "w": 1280, "h": 1816}, {"t": "j", "w": 1280, "h": 1816}, {"t": "j", "w": 1280, "h": 1816}, {"t": "j", "w": 1280, "h": 1816}, {"t": "j", "w": 1280, "h": 1816}, {"t": "j", "w": 1280, "h": 1816}, {"t": "j", "w": 1280, "h": 1816}, {"t": "j", "w": 1280, "h": 1816}, {"t": "j", "w": 1280, "h": 1816}, {"t": "j", "w": 1280, "h": 1816}, {"t": "j", "w": 1280, "h": 1816}, {"t": "j", "w": 1280, "h": 1816}, {"t": "j", "w": 1280, "h": 1816}, {"t": "j", "w": 1280, "h": 1816}, {"t": "j", "w": 1280, "h": 1816}, {"t": "j", "w": 1280, "h": 1816}, {"t": "j", "w": 1280, "h": 1816}, {"t": "j", "w": 1280, "h": 1816}, {"t": "j", "w": 1280, "h": 1816}, {"t": "j", "w": 1280, "h": 1816}, {"t": "j", "w": 1280, "h": 1816}, {"t": "j", "w": 1280, "h": 1816}, {"t": "j", "w": 1280, "h": 1816}, {"t": "j", "w": 1280, "h": 1816}, {"t": "j", "w": 1280, "h": 1816}, {"t": "j", "w": 1280, "h": 1816}, {"t": "j", "w": 1280, "h": 1816}, {"t": "j", "w": 1280, "h": 1816}, {"t": "j", "w": 1280, "h": 1816}, {"t": "j", "w": 1280, "h": 1816}, {"t": "j", "w": 1280, "h": 1816}, {"t": "j", "w": 1280, "h": 1816}, {"t": "j", "w": 1280, "h": 1816}, {"t": "j", "w": 1280, "h": 1816}, {"t": "j", "w": 1280, "h": 1816}, {"t": "j", "w": 1280, "h": 1816}, {"t": "j", "w": 1280, "h": 1816}, {"t": "j", "w": 1280, "h": 1816}, {"t": "j", "w": 1280, "h": 1816}, {"t": "j", "w": 1280, "h": 1816}, {"t": "j", "w": 1280, "h": 1816}, {"t": "j", "w": 1280, "h": 1816}, {"t": "j", "w": 1280, "h": 1816}, {"t": "j", "w": 1280, "h": 1816}, {"t": "j", "w": 1280, "h": 1816}, {"t": "j", "w": 1280, "h": 1816}, {"t": "j", "w": 1280, "h": 1816}, {"t": "j", "w": 1280, "h": 1816}, {"t": "j", "w": 1280, "h": 1816}, {"t": "j", "w": 1280, "h": 1816}, {"t": "j", "w": 1280, "h": 1816}, {"t": "j", "w": 1280, "h": 1816}, {"t": "j", "w": 1280, "h": 1816}, {"t": "j", "w": 1280, "h": 1816}, {"t": "j", "w": 1280, "h": 1816}, {"t": "j", "w": 1280, "h": 1816}, {"t": "j", "w": 1280, "h": 1816}, {"t": "j", "w": 1280, "h": 1816}, {"t": "j", "w": 1280, "h": 1816}, {"t": "j", "w": 1280, "h": 1816}, {"t": "j", "w": 1280, "h": 1816}, {"t": "j", "w": 1280, "h": 1816}, {"t": "j", "w": 1280, "h": 1816}, {"t": "j", "w": 1280, "h": 1816}, {"t": "j", "w": 1280, "h": 1816}, {"t": "j", "w": 1280, "h": 1816}, {"t": "j", "w": 1280, "h": 1816}, {"t": "j", "w": 1280, "h": 1816}, {"t": "j", "w": 1280, "h": 1816}, {"t": "j", "w": 1280, "h": 1816}, {"t": "j", "w": 1280, "h": 1816}, {"t": "j", "w": 1280, "h": 1816}, {"t": "j", "w": 1280, "h": 1816}, {"t": "j", "w": 1280, "h": 1816}, {"t": "j", "w": 1280, "h": 1816}, {"t": "j", "w": 1280, "h": 1816}, {"t": "j", "w": 1280, "h": 1816}, {"t": "j", "w": 1280, "h": 1816}, {"t": "j", "w": 1280, "h": 1816}, {"t": "j", "w": 1280, "h": 1816}, {"t": "j", "w": 1280, "h": 1816}, {"t": "j", "w": 1280, "h": 1816}], "cover": {"t": "j", "w": 350, "h": 496}, "thumbnail": {"t": "j", "w": 250, "h": 354}}, "scanlator": "", "upload_date": 1693829710, "tags": [{"id": 779, "type": "tag", "name": "futanari", "url": "/tag/futanari/", "count": 32379}, {"id": 2937, "type": "tag", "name": "big breasts", "url": "/tag/big-breasts/", "count": 158961}, {"id": 6346, "type": "language", "name": "japanese", "url": "/language/japanese/", "count": 262842}, {"id": 8378, "type": "tag", "name": "glasses", "url": "/tag/glasses/", "count": 65954}, {"id": 10314, "type": "tag", "name": "schoolgirl uniform", "url": "/tag/schoolgirl-uniform/", "count": 75189}, {"id": 10988, "type": "tag", "name": "anthology", "url": "/tag/anthology/", "count": 11997}, {"id": 14283, "type": "tag", "name": "anal", "url": "/tag/anal/", "count": 95222}, {"id": 14971, "type": "tag", "name": "sex toys", "url": "/tag/sex-toys/", "count": 31034}, {"id": 16999, "type": "artist", "name": "musashi daichi", "url": "/artist/musashi-daichi/", "count": 174}, {"id": 22942, "type": "tag", "name": "incest", "url": "/tag/incest/", "count": 41010}, {"id": 29182, "type": "tag", "name": "blackmail", "url": "/tag/blackmail/", "count": 8278}, {"id": 29407, "type": "artist", "name": "nyuuhin", "url": "/artist/nyuuhin/", "count": 96}, {"id": 29859, "type": "tag", "name": "blowjob", "url": "/tag/blowjob/", "count": 68056}, {"id": 30035, "type": "tag", "name": "gender bender", "url": "/tag/gender-bender/", "count": 11441}, {"id": 33173, "type": "category", "name": "manga", "url": "/category/manga/", "count": 113130}, {"id": 35968, "type": "tag", "name": "dickgirl on male", "url": "/tag/dickgirl-on-male/", "count": 3781}, {"id": 35970, "type": "tag", "name": "dickgirl on dickgirl", "url": "/tag/dickgirl-on-dickgirl/", "count": 4463}, {"id": 35971, "type": "tag", "name": "male on dickgirl", "url": "/tag/male-on-dickgirl/", "count": 2849}, {"id": 81774, "type": "tag", "name": "kemonomimi", "url": "/tag/kemonomimi/", "count": 16744}, {"id": 130025, "type": "tag", "name": "anal intercourse", "url": "/tag/anal-intercourse/", "count": 12186}, {"id": 130503, "type": "artist", "name": "puru", "url": "/artist/puru/", "count": 10}, {"id": 135869, "type": "artist", "name": "kuramoto zen", "url": "/artist/kuramoto-zen/", "count": 6}, {"id": 137224, "type": "tag", "name": "gender morph", "url": "/tag/gender-morph/", "count": 635}, {"id": 145458, "type": "tag", "name": "kozuki kanna", "url": "/tag/kozuki-kanna/", "count": 2}, {"id": 149292, "type": "tag", "name": "penis enlargement", "url": "/tag/penis-enlargement/", "count": 115}], "num_pages": 82, "num_favorites": 1657}, {"id": 471570, "media_id": "2664261", "title": {"english": "[Akireru Shoujo (Akire)] Boku dake ni Amaesasete Kureru Kyonyuu JK Tsuma o Hoka no Otoko ni Dakasete Mita 8  [English] [hardcase8translates]", "japanese": "[アキレルショウジョ (アキレ)] 僕だけに甘えさせてくれる巨乳Jk妻を他の男に抱かせてみた8 [英訳]", "pretty": "Boku dake ni Amaesasete Kureru Kyonyuu JK Tsuma o Hoka no Otoko ni Dakasete Mita 8"}, "images": {"pages": [{"t": "p", "w": 1280, "h": 1810}, {"t": "p", "w": 1280, "h": 1810}, {"t": "p", "w": 1280, "h": 1810}, {"t": "p", "w": 1280, "h": 1810}, {"t": "p", "w": 1280, "h": 1810}, {"t": "p", "w": 1280, "h": 1810}, {"t": "p", "w": 1280, "h": 1810}, {"t": "p", "w": 1280, "h": 1810}, {"t": "p", "w": 1280, "h": 1810}, {"t": "p", "w": 1280, "h": 1810}, {"t": "p", "w": 1280, "h": 1810}, {"t": "p", "w": 1280, "h": 1810}, {"t": "p", "w": 1280, "h": 1810}, {"t": "p", "w": 1280, "h": 1810}, {"t": "p", "w": 1280, "h": 1810}, {"t": "p", "w": 1280, "h": 1810}, {"t": "p", "w": 1280, "h": 1810}, {"t": "p", "w": 1280, "h": 1810}, {"t": "p", "w": 1280, "h": 1810}, {"t": "p", "w": 1280, "h": 1810}, {"t": "p", "w": 1280, "h": 1810}, {"t": "p", "w": 1280, "h": 1810}, {"t": "p", "w": 1280, "h": 1810}, {"t": "p", "w": 1280, "h": 1810}, {"t": "p", "w": 1280, "h": 1810}, {"t": "p", "w": 1280, "h": 1810}, {"t": "p", "w": 1280, "h": 1810}, {"t": "p", "w": 1280, "h": 1810}, {"t": "p", "w": 1280, "h": 1810}, {"t": "p", "w": 1280, "h": 1810}, {"t": "p", "w": 1280, "h": 1810}, {"t": "p", "w": 1280, "h": 1810}, {"t": "p", "w": 1280, "h": 1810}, {"t": "p", "w": 1280, "h": 1810}, {"t": "p", "w": 1280, "h": 1810}, {"t": "p", "w": 1280, "h": 1810}, {"t": "p", "w": 1280, "h": 1810}, {"t": "p", "w": 1280, "h": 1810}, {"t": "p", "w": 1280, "h": 1810}, {"t": "p", "w": 1280, "h": 1810}, {"t": "p", "w": 1280, "h": 1810}, {"t": "p", "w": 1280, "h": 1810}, {"t": "p", "w": 1280, "h": 1810}, {"t": "p", "w": 1280, "h": 1810}, {"t": "j", "w": 1280, "h": 631}], "cover": {"t": "p", "w": 350, "h": 495}, "thumbnail": {"t": "p", "w": 250, "h": 354}}, "scanlator": "", "upload_date": 1693829130, "tags": [{"id": 2633, "type": "tag", "name": "leg lock", "url": "/tag/leg-lock/", "count": 3029}, {"id": 2937, "type": "tag", "name": "big breasts", "url": "/tag/big-breasts/", "count": 159771}, {"id": 7155, "type": "tag", "name": "cunnilingus", "url": "/tag/cunnilingus/", "count": 9325}, {"id": 9260, "type": "tag", "name": "cheating", "url": "/tag/cheating/", "count": 21258}, {"id": 12227, "type": "language", "name": "english", "url": "/language/english/", "count": 109621}, {"id": 12824, "type": "tag", "name": "condom", "url": "/tag/condom/", "count": 11200}, {"id": 17249, "type": "language", "name": "translated", "url": "/language/translated/", "count": 195257}, {"id": 21572, "type": "tag", "name": "multi-work series", "url": "/tag/multi-work-series/", "count": 33418}, {"id": 24102, "type": "tag", "name": "lactation", "url": "/tag/lactation/", "count": 17225}, {"id": 25614, "type": "tag", "name": "paizuri", "url": "/tag/paizuri/", "count": 33079}, {"id": 29013, "type": "tag", "name": "dilf", "url": "/tag/dilf/", "count": 24236}, {"id": 29859, "type": "tag", "name": "blowjob", "url": "/tag/blowjob/", "count": 68417}, {"id": 33172, "type": "category", "name": "doujinshi", "url": "/category/doujinshi/", "count": 356060}, {"id": 35762, "type": "tag", "name": "sole female", "url": "/tag/sole-female/", "count": 131165}, {"id": 35763, "type": "tag", "name": "sole male", "url": "/tag/sole-male/", "count": 116519}, {"id": 73750, "type": "tag", "name": "bald", "url": "/tag/bald/", "count": 6550}, {"id": 90671, "type": "parody", "name": "original", "url": "/parody/original/", "count": 75230}, {"id": 107705, "type": "tag", "name": "facial hair", "url": "/tag/facial-hair/", "count": 2859}, {"id": 114164, "type": "group", "name": "akirerushoujo", "url": "/group/akirerushoujo/", "count": 59}, {"id": 114197, "type": "artist", "name": "akire", "url": "/artist/akire/", "count": 62}, {"id": 141098, "type": "tag", "name": "nipple stimulation", "url": "/tag/nipple-stimulation/", "count": 1471}], "num_pages": 45, "num_favorites": 5835}, {"id": 471569, "media_id": "2664259", "title": {"english": "[Anthology] Digital Puni Pedo! Vol. 28", "japanese": "[アンソロジー] デジタルぷにぺどッ! Vol.28", "pretty": "Digital Puni Pedo! Vol. 28"}, "images": {"pages": [{"t": "j", "w": 1280, "h": 1816}, {"t": "j", "w": 1280, "h": 1816}, {"t": "j", "w": 1280, "h": 1816}, {"t": "j", "w": 1280, "h": 1816}, {"t": "j", "w": 1280, "h": 1816}, {"t": "j", "w": 1280, "h": 1816}, {"t": "j", "w": 1280, "h": 1816}, {"t": "j", "w": 1280, "h": 1816}, {"t": "j", "w": 1280, "h": 1816}, {"t": "j", "w": 1280, "h": 1816}, {"t": "j", "w": 1280, "h": 1816}, {"t": "j", "w": 1280, "h": 1816}, {"t": "j", "w": 1280, "h": 1816}, {"t": "j", "w": 1280, "h": 1816}, {"t": "j", "w": 1280, "h": 1816}, {"t": "j", "w": 1280, "h": 1816}, {"t": "j", "w": 1280, "h": 1816}, {"t": "j", "w": 1280, "h": 1816}, {"t": "j", "w": 1280, "h": 1816}, {"t": "j", "w": 1280, "h": 1816}, {"t": "j", "w": 1280, "h": 1816}, {"t": "j", "w": 1280, "h": 1816}, {"t": "j", "w": 1280, "h": 1816}, {"t": "j", "w": 1280, "h": 1816}, {"t": "j", "w": 1280, "h": 1816}, {"t": "j", "w": 1280, "h": 1816}, {"t": "j", "w": 1280, "h": 1816}, {"t": "j", "w": 1280, "h": 1816}, {"t": "j", "w": 1280, "h": 1816}, {"t": "j", "w": 1280, "h": 1816}, {"t": "j", "w": 1280, "h": 1816}, {"t": "j", "w": 1280, "h": 1816}, {"t": "j", "w": 1280, "h": 1816}, {"t": "j", "w": 1280, "h": 1816}, {"t": "j", "w": 1280, "h": 1816}, {"t": "j", "w": 1280, "h": 1816}, {"t": "j", "w": 1280, "h": 1816}, {"t": "j", "w": 1280, "h": 1816}, {"t": "j", "w": 1280, "h": 1816}, {"t": "j", "w": 1280, "h": 1816}, {"t": "j", "w": 1280, "h": 1816}, {"t": "j", "w": 1280, "h": 1816}, {"t": "j", "w": 1280, "h": 1816}, {"t": "j", "w": 1280, "h": 1816}, {"t": "j", "w": 1280, "h": 1816}, {"t": "j", "w": 1280, "h": 1816}, {"t": "j", "w": 1280, "h": 1816}, {"t": "j", "w": 1280, "h": 1816}, {"t": "j", "w": 1280, "h": 1816}, {"t": "j", "w": 1280, "h": 1816}, {"t": "j", "w": 1280, "h": 1816}, {"t": "j", "w": 1280, "h": 1816}, {"t": "j", "w": 1280, "h": 1816}, {"t": "j", "w": 1280, "h": 1816}, {"t": "j", "w": 1280, "h": 1816}, {"t": "j", "w": 1280, "h": 1816}, {"t": "j", "w": 1280, "h": 1816}, {"t": "j", "w": 1280, "h": 1816}, {"t": "j", "w": 1280, "h": 1816}, {"t": "j", "w": 1280, "h": 1816}, {"t": "j", "w": 1280, "h": 1816}, {"t": "j", "w": 1280, "h": 1816}, {"t": "j", "w": 1280, "h": 1816}, {"t": "j", "w": 1280, "h": 1816}, {"t": "j", "w": 1280, "h": 1816}, {"t": "j", "w": 1280, "h": 1816}, {"t": "j", "w": 1280, "h": 1816}, {"t": "j", "w": 1280, "h": 1816}, {"t": "j", "w": 1280, "h": 1816}, {"t": "j", "w": 1280, "h": 1816}, {"t": "j", "w": 1280, "h": 1816}, {"t": "j", "w": 1280, "h": 1816}, {"t": "j", "w": 1280, "h": 1816}, {"t": "j", "w": 1280, "h": 1816}, {"t": "j", "w": 1280, "h": 1816}, {"t": "j", "w": 1280, "h": 1816}, {"t": "j", "w": 1280, "h": 1816}, {"t": "j", "w": 1280, "h": 1816}, {"t": "j", "w": 1280, "h": 1816}, {"t": "j", "w": 1280, "h": 1816}, {"t": "j", "w": 1280, "h": 1816}, {"t": "j", "w": 1280, "h": 1816}, {"t": "j", "w": 1280, "h": 1816}, {"t": "j", "w": 1280, "h": 1816}, {"t": "j", "w": 1280, "h": 1816}, {"t": "j", "w": 1280, "h": 1816}, {"t": "j", "w": 1280, "h": 1816}, {"t": "j", "w": 1280, "h": 1816}, {"t": "j", "w": 1280, "h": 1816}, {"t": "j", "w": 1280, "h": 1816}, {"t": "j", "w": 1280, "h": 1816}, {"t": "j", "w": 1280, "h": 1816}, {"t": "j", "w": 1280, "h": 1816}, {"t": "j", "w": 1280, "h": 1816}, {"t": "j", "w": 1280, "h": 1816}, {"t": "j", "w": 1280, "h": 1816}, {"t": "j", "w": 1280, "h": 1816}, {"t": "j", "w": 1280, "h": 1816}, {"t": "j", "w": 1280, "h": 1816}, {"t": "j", "w": 1280, "h": 1816}, {"t": "j", "w": 1280, "h": 1816}, {"t": "j", "w": 1280, "h": 1816}, {"t": "j", "w": 1280, "h": 1816}, {"t": "j", "w": 1280, "h": 1816}, {"t": "j", "w": 1280, "h": 1816}, {"t": "j", "w": 1280, "h": 1816}, {"t": "j", "w": 1280, "h": 1816}, {"t": "j", "w": 1280, "h": 1816}, {"t": "j", "w": 1280, "h": 1816}, {"t": "j", "w": 1280, "h": 1816}, {"t": "j", "w": 1280, "h": 1816}, {"t": "j", "w": 1280, "h": 1816}, {"t": "j", "w": 1280, "h": 1816}, {"t": "j", "w": 1280, "h": 1816}], "cover": {"t": "j", "w": 350, "h": 496}, "thumbnail": {"t": "j", "w": 250, "h": 354}}, "scanlator": "", "upload_date": 1693828807, "tags": [{"id": 6346, "type": "language", "name": "japanese", "url": "/language/japanese/", "count": 263704}, {"id": 10988, "type": "tag", "name": "anthology", "url": "/tag/anthology/", "count": 12031}, {"id": 19440, "type": "tag", "name": "lolicon", "url": "/tag/lolicon/", "count": 92054}, {"id": 23055, "type": "artist", "name": "maki daikichi", "url": "/artist/maki-daikichi/", "count": 108}, {"id": 28031, "type": "tag", "name": "sister", "url": "/tag/sister/", "count": 20173}, {"id": 33173, "type": "category", "name": "manga", "url": "/category/manga/", "count": 113710}, {"id": 37150, "type": "artist", "name": "akiha", "url": "/artist/akiha/", "count": 21}, {"id": 50790, "type": "artist", "name": "arai togami", "url": "/artist/arai-togami/", "count": 43}, {"id": 57110, "type": "artist", "name": "yashiro ryo", "url": "/artist/yashiro-ryo/", "count": 13}, {"id": 82888, "type": "artist", "name": "bookmoun10", "url": "/artist/bookmoun10/", "count": 67}, {"id": 96371, "type": "artist", "name": "zun nyannyan", "url": "/artist/zun-nyannyan/", "count": 26}, {"id": 148525, "type": "artist", "name": "kaisenbatake no yuu", "url": "/artist/kaisenbatake-no-yuu/", "count": 3}], "num_pages": 114, "num_favorites": 1086}, {"id": 471568, "media_id": "2664254", "title": {"english": "[Ringoya (Alp)] C102 Omakebon (Goddess of Victory: Nikke) [Chinese] [王の木×迪奥的黄金呆毛个人汉化] [Digital]", "japanese": "[リンゴヤ (あるぷ)] C102 おまけ本 (勝利の女神:NIKKE) [中国翻訳] [DL版]", "pretty": "C102 Omakebon"}, "images": {"pages": [{"t": "j", "w": 921, "h": 1300}, {"t": "j", "w": 935, "h": 1300}, {"t": "j", "w": 935, "h": 1300}, {"t": "j", "w": 935, "h": 1300}, {"t": "j", "w": 935, "h": 1300}, {"t": "j", "w": 935, "h": 1300}, {"t": "j", "w": 935, "h": 1300}, {"t": "j", "w": 935, "h": 1300}, {"t": "j", "w": 935, "h": 1300}, {"t": "j", "w": 935, "h": 1300}, {"t": "j", "w": 935, "h": 1300}, {"t": "j", "w": 935, "h": 1300}, {"t": "j", "w": 935, "h": 1300}, {"t": "j", "w": 921, "h": 1300}], "cover": {"t": "j", "w": 350, "h": 494}, "thumbnail": {"t": "j", "w": 250, "h": 353}}, "scanlator": "", "upload_date": 1693827375, "tags": [{"id": 5875, "type": "group", "name": "ringoya", "url": "/group/ringoya/", "count": 188}, {"id": 17249, "type": "language", "name": "translated", "url": "/language/translated/", "count": 195366}, {"id": 22786, "type": "artist", "name": "alp", "url": "/artist/alp/", "count": 320}, {"id": 29963, "type": "language", "name": "chinese", "url": "/language/chinese/", "count": 97324}, {"id": 33172, "type": "category", "name": "doujinshi", "url": "/category/doujinshi/", "count": 356214}, {"id": 35762, "type": "tag", "name": "sole female", "url": "/tag/sole-female/", "count": 131259}, {"id": 35763, "type": "tag", "name": "sole male", "url": "/tag/sole-male/", "count": 116598}, {"id": 92923, "type": "character", "name": "shikikan", "url": "/character/shikikan/", "count": 915}, {"id": 144055, "type": "parody", "name": "goddess of victory nikke", "url": "/parody/goddess-of-victory-nikke/", "count": 94}, {"id": 144341, "type": "character", "name": "anis", "url": "/character/anis/", "count": 22}], "num_pages": 14, "num_favorites": 2596}, {"id": 471567, "media_id": "2664247", "title": {"english": "[Pfactory (Pikachurin)] Junjou Thoroughbred Shukuhaku Gakushuu Hen NEXT [Digital]", "japanese": "[Pfactory (ピカチュリン)] 純情サラブレッド 宿泊学習編NEXT [DL版]", "pretty": "Junjou Thoroughbred Shukuhaku Gakushuu Hen NEXT"}, "images": {"pages": [{"t": "j", "w": 1280, "h": 904}, {"t": "j", "w": 1280, "h": 1780}, {"t": "j", "w": 1280, "h": 1780}, {"t": "j", "w": 1280, "h": 1780}, {"t": "j", "w": 1280, "h": 1780}, {"t": "j", "w": 1280, "h": 1780}, {"t": "j", "w": 1280, "h": 1780}, {"t": "j", "w": 1280, "h": 1780}, {"t": "j", "w": 1280, "h": 1780}, {"t": "j", "w": 1280, "h": 1780}, {"t": "j", "w": 1280, "h": 1780}, {"t": "j", "w": 1280, "h": 1780}, {"t": "j", "w": 1280, "h": 1780}, {"t": "j", "w": 1280, "h": 1780}, {"t": "j", "w": 1280, "h": 1780}, {"t": "j", "w": 1280, "h": 1780}, {"t": "j", "w": 1280, "h": 1780}, {"t": "j", "w": 1280, "h": 1780}, {"t": "j", "w": 1280, "h": 1780}, {"t": "j", "w": 1280, "h": 1780}, {"t": "j", "w": 1280, "h": 1780}, {"t": "j", "w": 1280, "h": 1780}, {"t": "j", "w": 1280, "h": 1780}, {"t": "j", "w": 1280, "h": 1780}, {"t": "j", "w": 1280, "h": 1780}, {"t": "j", "w": 1280, "h": 1780}, {"t": "j", "w": 1280, "h": 1780}, {"t": "j", "w": 1280, "h": 1780}, {"t": "j", "w": 1280, "h": 1780}, {"t": "j", "w": 1280, "h": 1780}, {"t": "j", "w": 1280, "h": 1780}, {"t": "j", "w": 1280, "h": 1780}, {"t": "j", "w": 1280, "h": 1780}, {"t": "j", "w": 1280, "h": 1780}, {"t": "j", "w": 1280, "h": 1780}, {"t": "j", "w": 1280, "h": 1780}, {"t": "j", "w": 1280, "h": 1780}], "cover": {"t": "j", "w": 350, "h": 247}, "thumbnail": {"t": "j", "w": 250, "h": 176}}, "scanlator": "", "upload_date": 1693827252, "tags": [{"id": 1033, "type": "tag", "name": "handjob", "url": "/tag/handjob/", "count": 11080}, {"id": 6346, "type": "language", "name": "japanese", "url": "/language/japanese/", "count": 261923}, {"id": 13640, "type": "tag", "name": "frottage", "url": "/tag/frottage/", "count": 1796}, {"id": 17501, "type": "tag", "name": "phimosis", "url": "/tag/phimosis/", "count": 1250}, {"id": 21572, "type": "tag", "name": "multi-work series", "url": "/tag/multi-work-series/", "count": 32827}, {"id": 21712, "type": "tag", "name": "males only", "url": "/tag/males-only/", "count": 39446}, {"id": 23895, "type": "tag", "name": "yaoi", "url": "/tag/yaoi/", "count": 46654}, {"id": 32341, "type": "tag", "name": "shotacon", "url": "/tag/shotacon/", "count": 54436}, {"id": 33172, "type": "category", "name": "doujinshi", "url": "/category/doujinshi/", "count": 352958}, {"id": 75060, "type": "group", "name": "pfactory", "url": "/group/pfactory/", "count": 38}, {"id": 75061, "type": "artist", "name": "pikachurin", "url": "/artist/pikachurin/", "count": 38}, {"id": 90671, "type": "parody", "name": "original", "url": "/parody/original/", "count": 73408}, {"id": 104245, "type": "tag", "name": "small penis", "url": "/tag/small-penis/", "count": 1316}, {"id": 106119, "type": "tag", "name": "no penetration", "url": "/tag/no-penetration/", "count": 3962}], "num_pages": 37, "num_favorites": 231}, {"id": 471566, "media_id": "2664240", "title": {"english": "[GEORUKKA (Gekokura)] Tasuketekureta Ningyo no Mesu Onii-san to Icha Icha suru Hon", "japanese": "[GEORUKKA (下戸蔵)] 助けてくれた人魚のメスお兄さんとイチャイチャする本 [DL版]", "pretty": "Tasuketekureta Ningyo no Mesu Onii-san to Icha Icha suru Hon"}, "images": {"pages": [{"t": "j", "w": 1280, "h": 1807}, {"t": "j", "w": 1280, "h": 1807}, {"t": "j", "w": 1280, "h": 1807}, {"t": "j", "w": 1280, "h": 1807}, {"t": "j", "w": 1280, "h": 1807}, {"t": "j", "w": 1280, "h": 1807}, {"t": "j", "w": 1280, "h": 1807}, {"t": "j", "w": 1280, "h": 1807}, {"t": "j", "w": 1280, "h": 1807}, {"t": "j", "w": 1280, "h": 1807}, {"t": "j", "w": 1280, "h": 1807}, {"t": "j", "w": 1280, "h": 1807}, {"t": "j", "w": 1280, "h": 1807}, {"t": "j", "w": 1280, "h": 1807}, {"t": "j", "w": 1280, "h": 1807}, {"t": "j", "w": 1280, "h": 1807}, {"t": "j", "w": 1280, "h": 1807}, {"t": "j", "w": 1280, "h": 1807}, {"t": "j", "w": 1280, "h": 1807}, {"t": "j", "w": 1280, "h": 1807}, {"t": "j", "w": 1280, "h": 1807}, {"t": "j", "w": 1280, "h": 1807}, {"t": "j", "w": 1280, "h": 1807}], "cover": {"t": "j", "w": 350, "h": 494}, "thumbnail": {"t": "j", "w": 250, "h": 353}}, "scanlator": "", "upload_date": 1693826752, "tags": [{"id": 6346, "type": "language", "name": "japanese", "url": "/language/japanese/", "count": 263704}, {"id": 12031, "type": "tag", "name": "cuntboy", "url": "/tag/cuntboy/", "count": 232}, {"id": 18567, "type": "tag", "name": "monster", "url": "/tag/monster/", "count": 6076}, {"id": 21712, "type": "tag", "name": "males only", "url": "/tag/males-only/", "count": 39818}, {"id": 21903, "type": "tag", "name": "merman", "url": "/tag/merman/", "count": 70}, {"id": 23895, "type": "tag", "name": "yaoi", "url": "/tag/yaoi/", "count": 47057}, {"id": 29023, "type": "tag", "name": "tomgirl", "url": "/tag/tomgirl/", "count": 16389}, {"id": 33172, "type": "category", "name": "doujinshi", "url": "/category/doujinshi/", "count": 356214}, {"id": 90671, "type": "parody", "name": "original", "url": "/parody/original/", "count": 75331}, {"id": 147606, "type": "group", "name": "georukka", "url": "/group/georukka/", "count": 2}, {"id": 147607, "type": "artist", "name": "gekokura", "url": "/artist/gekokura/", "count": 2}], "num_pages": 23, "num_favorites": 570}, {"id": 471565, "media_id": "2664235", "title": {"english": "[Mousou Hunter (Exabyte)] Direct☆Attack! (Yu-Gi-Oh!) [Digital]", "japanese": "[妄想ハンター (Exabyte)] Direct☆Attack! (遊☆戯☆王) [DL版]", "pretty": "Direct☆Attack!"}, "images": {"pages": [{"t": "j", "w": 1280, "h": 1807}, {"t": "j", "w": 1280, "h": 1807}, {"t": "j", "w": 1280, "h": 1808}, {"t": "j", "w": 1280, "h": 1808}, {"t": "j", "w": 1280, "h": 1808}, {"t": "j", "w": 1280, "h": 1808}, {"t": "j", "w": 1280, "h": 1808}, {"t": "j", "w": 1280, "h": 1808}, {"t": "j", "w": 1280, "h": 1808}, {"t": "j", "w": 1280, "h": 1808}, {"t": "j", "w": 1280, "h": 1808}, {"t": "j", "w": 1280, "h": 1808}, {"t": "j", "w": 1280, "h": 1808}, {"t": "j", "w": 1280, "h": 1808}, {"t": "j", "w": 1280, "h": 1808}, {"t": "j", "w": 1280, "h": 1808}, {"t": "j", "w": 1280, "h": 1808}, {"t": "j", "w": 1280, "h": 1808}, {"t": "j", "w": 1280, "h": 1808}, {"t": "j", "w": 1280, "h": 1808}, {"t": "j", "w": 1280, "h": 1808}, {"t": "j", "w": 1280, "h": 1808}, {"t": "j", "w": 1280, "h": 1808}, {"t": "j", "w": 1280, "h": 1808}, {"t": "j", "w": 1280, "h": 1807}, {"t": "j", "w": 1280, "h": 1807}], "cover": {"t": "j", "w": 350, "h": 494}, "thumbnail": {"t": "j", "w": 250, "h": 353}}, "scanlator": "", "upload_date": 1693826563, "tags": [{"id": 2937, "type": "tag", "name": "big breasts", "url": "/tag/big-breasts/", "count": 159530}, {"id": 6346, "type": "language", "name": "japanese", "url": "/language/japanese/", "count": 263406}, {"id": 7546, "type": "tag", "name": "witch", "url": "/tag/witch/", "count": 1387}, {"id": 8254, "type": "tag", "name": "horse boy", "url": "/tag/horse-boy/", "count": 79}, {"id": 9083, "type": "tag", "name": "big ass", "url": "/tag/big-ass/", "count": 16667}, {"id": 13924, "type": "parody", "name": "yu-gi-oh", "url": "/parody/yu-gi-oh/", "count": 719}, {"id": 13989, "type": "tag", "name": "ahegao", "url": "/tag/ahegao/", "count": 43879}, {"id": 14072, "type": "tag", "name": "huge breasts", "url": "/tag/huge-breasts/", "count": 12067}, {"id": 14283, "type": "tag", "name": "anal", "url": "/tag/anal/", "count": 95447}, {"id": 18567, "type": "tag", "name": "monster", "url": "/tag/monster/", "count": 6057}, {"id": 20617, "type": "tag", "name": "mind control", "url": "/tag/mind-control/", "count": 16626}, {"id": 22945, "type": "tag", "name": "double penetration", "url": "/tag/double-penetration/", "count": 33019}, {"id": 27553, "type": "tag", "name": "rape", "url": "/tag/rape/", "count": 49873}, {"id": 27680, "type": "character", "name": "silent magician", "url": "/character/silent-magician/", "count": 20}, {"id": 29859, "type": "tag", "name": "blowjob", "url": "/tag/blowjob/", "count": 68303}, {"id": 32484, "type": "tag", "name": "stomach deformation", "url": "/tag/stomach-deformation/", "count": 8168}, {"id": 33172, "type": "category", "name": "doujinshi", "url": "/category/doujinshi/", "count": 355630}, {"id": 35762, "type": "tag", "name": "sole female", "url": "/tag/sole-female/", "count": 130899}, {"id": 109856, "type": "artist", "name": "exabyte", "url": "/artist/exabyte/", "count": 14}, {"id": 121685, "type": "group", "name": "mousou hunter", "url": "/group/mousou-hunter/", "count": 12}], "num_pages": 26, "num_favorites": 1886}, {"id": 471564, "media_id": "2664233", "title": {"english": "[Pink Taro] Zetsubō Tsuma ~ Netori.", "japanese": "[ピンク太郎] 絶望妻～ネトリ。", "pretty": "Zetsubō Tsuma ~ Netori."}, "images": {"pages": [{"t": "j", "w": 1280, "h": 1811}, {"t": "j", "w": 1280, "h": 1808}, {"t": "j", "w": 1280, "h": 1808}, {"t": "j", "w": 1280, "h": 1810}, {"t": "j", "w": 1280, "h": 1807}, {"t": "j", "w": 1280, "h": 1808}, {"t": "j", "w": 1280, "h": 1808}, {"t": "j", "w": 1280, "h": 1816}, {"t": "j", "w": 1280, "h": 1811}, {"t": "j", "w": 1280, "h": 1808}, {"t": "j", "w": 1280, "h": 1811}, {"t": "j", "w": 1280, "h": 1811}, {"t": "j", "w": 1280, "h": 1810}, {"t": "j", "w": 1280, "h": 1801}, {"t": "j", "w": 1280, "h": 1812}, {"t": "j", "w": 1280, "h": 1809}, {"t": "j", "w": 1280, "h": 1808}, {"t": "j", "w": 1280, "h": 1811}, {"t": "j", "w": 1280, "h": 1801}], "cover": {"t": "j", "w": 350, "h": 495}, "thumbnail": {"t": "j", "w": 250, "h": 354}}, "scanlator": "", "upload_date": 1693826360, "tags": [{"id": 370, "type": "tag", "name": "business suit", "url": "/tag/business-suit/", "count": 5267}, {"id": 1643, "type": "tag", "name": "kissing", "url": "/tag/kissing/", "count": 11933}, {"id": 6346, "type": "language", "name": "japanese", "url": "/language/japanese/", "count": 263406}, {"id": 16447, "type": "artist", "name": "pink taro", "url": "/artist/pink-taro/", "count": 81}, {"id": 21572, "type": "tag", "name": "multi-work series", "url": "/tag/multi-work-series/", "count": 33336}, {"id": 26953, "type": "tag", "name": "bukkake", "url": "/tag/bukkake/", "count": 6985}, {"id": 33173, "type": "category", "name": "manga", "url": "/category/manga/", "count": 113482}, {"id": 35762, "type": "tag", "name": "sole female", "url": "/tag/sole-female/", "count": 130899}, {"id": 35763, "type": "tag", "name": "sole male", "url": "/tag/sole-male/", "count": 116268}], "num_pages": 19, "num_favorites": 390}, {"id": 471563, "media_id": "2664214", "title": {"english": "[Kise Itsuki] \"Uso, Ichiban Oku made Sounyuutteru...\" Kare no Kouhai kara Ikasarete... Uwaki SEX de Ochiru Yoru 1", "japanese": "[木瀬樹]「うそっ、一番奥まで挿入ってる…」 彼の後輩からイカされて…浮気SEXで堕ちる夜 1", "pretty": "\"Uso, Ichiban Oku made Sounyuutteru...\" Kare no Kouhai kara Ikasarete... Uwaki SEX de Ochiru Yoru 1"}, "images": {"pages": [{"t": "j", "w": 1280, "h": 1814}, {"t": "j", "w": 1280, "h": 1803}, {"t": "j", "w": 1280, "h": 1809}, {"t": "j", "w": 1280, "h": 1814}, {"t": "j", "w": 1280, "h": 1823}, {"t": "j", "w": 1280, "h": 1819}, {"t": "j", "w": 1280, "h": 1815}, {"t": "j", "w": 1280, "h": 1818}, {"t": "j", "w": 1280, "h": 1819}, {"t": "j", "w": 1280, "h": 1799}, {"t": "j", "w": 1280, "h": 1820}, {"t": "j", "w": 1280, "h": 1844}, {"t": "j", "w": 1280, "h": 1827}, {"t": "j", "w": 1280, "h": 1818}, {"t": "j", "w": 1280, "h": 1785}, {"t": "j", "w": 1280, "h": 1817}, {"t": "j", "w": 1280, "h": 1825}, {"t": "j", "w": 1280, "h": 1819}, {"t": "j", "w": 1280, "h": 1813}, {"t": "j", "w": 1280, "h": 1823}, {"t": "j", "w": 1280, "h": 1872}, {"t": "j", "w": 1280, "h": 1818}, {"t": "j", "w": 1280, "h": 1819}, {"t": "j", "w": 1280, "h": 1819}, {"t": "j", "w": 1280, "h": 1811}, {"t": "j", "w": 1280, "h": 1817}, {"t": "j", "w": 1280, "h": 1830}, {"t": "j", "w": 1280, "h": 1843}], "cover": {"t": "j", "w": 350, "h": 496}, "thumbnail": {"t": "j", "w": 250, "h": 354}}, "scanlator": "", "upload_date": 1693826207, "tags": [{"id": 6346, "type": "language", "name": "japanese", "url": "/language/japanese/", "count": 263704}, {"id": 8368, "type": "tag", "name": "full censorship", "url": "/tag/full-censorship/", "count": 26735}, {"id": 8653, "type": "tag", "name": "netorare", "url": "/tag/netorare/", "count": 28817}, {"id": 9260, "type": "tag", "name": "cheating", "url": "/tag/cheating/", "count": 21282}, {"id": 21572, "type": "tag", "name": "multi-work series", "url": "/tag/multi-work-series/", "count": 33449}, {"id": 26130, "type": "tag", "name": "fingering", "url": "/tag/fingering/", "count": 10695}, {"id": 33173, "type": "category", "name": "manga", "url": "/category/manga/", "count": 113710}, {"id": 35762, "type": "tag", "name": "sole female", "url": "/tag/sole-female/", "count": 131260}, {"id": 35763, "type": "tag", "name": "sole male", "url": "/tag/sole-male/", "count": 116600}, {"id": 125433, "type": "artist", "name": "kise itsuki", "url": "/artist/kise-itsuki/", "count": 40}], "num_pages": 28, "num_favorites": 525}, {"id": 471562, "media_id": "2664204", "title": {"english": "[The Nation of Head Scissors (Toppogi)] Girls Beat! Plus vs Nami", "japanese": "[The Nation of Head Scissors (トッポギ)] Girls Beat! ぷらす vs ナミ", "pretty": "Girls Beat! Plus vs Nami"}, "images": {"pages": [{"t": "j", "w": 1280, "h": 905}, {"t": "j", "w": 1280, "h": 905}, {"t": "j", "w": 1240, "h": 1754}, {"t": "j", "w": 1240, "h": 1754}, {"t": "j", "w": 1240, "h": 1754}, {"t": "j", "w": 1240, "h": 1754}, {"t": "j", "w": 1240, "h": 1754}, {"t": "j", "w": 1240, "h": 1754}, {"t": "j", "w": 1240, "h": 1754}, {"t": "j", "w": 1240, "h": 1754}, {"t": "j", "w": 1240, "h": 1754}, {"t": "j", "w": 1240, "h": 1754}, {"t": "j", "w": 1240, "h": 1754}, {"t": "j", "w": 1240, "h": 1754}, {"t": "j", "w": 1240, "h": 1754}, {"t": "j", "w": 1240, "h": 1754}, {"t": "j", "w": 1240, "h": 1754}, {"t": "j", "w": 1240, "h": 1754}, {"t": "j", "w": 1240, "h": 1754}, {"t": "j", "w": 1240, "h": 1754}], "cover": {"t": "j", "w": 350, "h": 248}, "thumbnail": {"t": "j", "w": 250, "h": 177}}, "scanlator": "", "upload_date": 1693825975, "tags": [{"id": 2820, "type": "tag", "name": "scat", "url": "/tag/scat/", "count": 8292}, {"id": 6346, "type": "language", "name": "japanese", "url": "/language/japanese/", "count": 263704}, {"id": 14069, "type": "tag", "name": "ryona", "url": "/tag/ryona/", "count": 3564}, {"id": 15408, "type": "tag", "name": "femdom", "url": "/tag/femdom/", "count": 25758}, {"id": 16518, "type": "tag", "name": "coprophagia", "url": "/tag/coprophagia/", "count": 979}, {"id": 25822, "type": "tag", "name": "smell", "url": "/tag/smell/", "count": 3521}, {"id": 28349, "type": "tag", "name": "cbt", "url": "/tag/cbt/", "count": 1905}, {"id": 33172, "type": "category", "name": "doujinshi", "url": "/category/doujinshi/", "count": 356214}, {"id": 35762, "type": "tag", "name": "sole female", "url": "/tag/sole-female/", "count": 131256}, {"id": 35763, "type": "tag", "name": "sole male", "url": "/tag/sole-male/", "count": 116595}, {"id": 72264, "type": "group", "name": "the nation of head scissors", "url": "/group/the-nation-of-head-scissors/", "count": 116}, {"id": 90671, "type": "parody", "name": "original", "url": "/parody/original/", "count": 75332}, {"id": 110568, "type": "artist", "name": "toppogi", "url": "/artist/toppogi/", "count": 168}], "num_pages": 20, "num_favorites": 393}, {"id": 471561, "media_id": "2664203", "title": {"english": "[Aoiramune (KLAI)] Sensei, zenbuo aishiteru (Genshin Impact) [Digital]", "japanese": "[青いラムネ (KLAI)] 先生、全部を愛してる (原神) [DL版]", "pretty": "Sensei, zenbuo aishiteru"}, "images": {"pages": [{"t": "j", "w": 1280, "h": 906}, {"t": "j", "w": 1280, "h": 1791}, {"t": "j", "w": 1280, "h": 1791}, {"t": "j", "w": 1280, "h": 1791}, {"t": "j", "w": 1280, "h": 1791}, {"t": "j", "w": 1280, "h": 1791}, {"t": "j", "w": 1280, "h": 1791}, {"t": "j", "w": 1280, "h": 1791}, {"t": "j", "w": 1280, "h": 1791}, {"t": "j", "w": 1280, "h": 1791}, {"t": "j", "w": 1280, "h": 1791}, {"t": "j", "w": 1280, "h": 1791}, {"t": "j", "w": 1280, "h": 1791}, {"t": "j", "w": 1280, "h": 1791}, {"t": "j", "w": 1280, "h": 1791}, {"t": "j", "w": 1280, "h": 1791}, {"t": "j", "w": 1280, "h": 1791}, {"t": "j", "w": 1280, "h": 1791}, {"t": "j", "w": 1280, "h": 1791}], "cover": {"t": "j", "w": 350, "h": 248}, "thumbnail": {"t": "j", "w": 250, "h": 177}}, "scanlator": "", "upload_date": 1693825817, "tags": [{"id": 6346, "type": "language", "name": "japanese", "url": "/language/japanese/", "count": 262719}, {"id": 21712, "type": "tag", "name": "males only", "url": "/tag/males-only/", "count": 39631}, {"id": 23895, "type": "tag", "name": "yaoi", "url": "/tag/yaoi/", "count": 46858}, {"id": 33172, "type": "category", "name": "doujinshi", "url": "/category/doujinshi/", "count": 354427}, {"id": 123503, "type": "parody", "name": "genshin impact", "url": "/parody/genshin-impact/", "count": 1938}, {"id": 129747, "type": "character", "name": "zhongli", "url": "/character/zhongli/", "count": 134}, {"id": 139639, "type": "character", "name": "tartaglia", "url": "/character/tartaglia/", "count": 89}], "num_pages": 19, "num_favorites": 197}, {"id": 471560, "media_id": "2664196", "title": {"english": "[Sevengar] Haisenkoku no Himegimi Shokushu ni Yori Koumon wo Kaihatsu sa reru [Chinese] [ANDX個人漢化]", "japanese": "[せぶんがー] 敗戦国の姫君、触手により肛門を開発される [中国翻訳]", "pretty": "Haisenkoku no Himegimi Shokushu ni Yori Koumon wo Kaihatsu sa reru"}, "images": {"pages": [{"t": "j", "w": 1280, "h": 1399}, {"t": "j", "w": 1280, "h": 1814}, {"t": "j", "w": 1280, "h": 1814}, {"t": "j", "w": 1280, "h": 1814}, {"t": "j", "w": 1280, "h": 1814}, {"t": "j", "w": 1280, "h": 1814}, {"t": "j", "w": 1280, "h": 1814}, {"t": "j", "w": 1280, "h": 1814}, {"t": "j", "w": 1280, "h": 1814}], "cover": {"t": "j", "w": 350, "h": 382}, "thumbnail": {"t": "j", "w": 250, "h": 273}}, "scanlator": "", "upload_date": 1693825665, "tags": [{"id": 2937, "type": "tag", "name": "big breasts", "url": "/tag/big-breasts/", "count": 158844}, {"id": 14283, "type": "tag", "name": "anal", "url": "/tag/anal/", "count": 95152}, {"id": 15658, "type": "tag", "name": "bondage", "url": "/tag/bondage/", "count": 46534}, {"id": 17249, "type": "language", "name": "translated", "url": "/language/translated/", "count": 194015}, {"id": 29963, "type": "language", "name": "chinese", "url": "/language/chinese/", "count": 96393}, {"id": 31775, "type": "tag", "name": "tentacles", "url": "/tag/tentacles/", "count": 18412}, {"id": 33172, "type": "category", "name": "doujinshi", "url": "/category/doujinshi/", "count": 354427}, {"id": 35762, "type": "tag", "name": "sole female", "url": "/tag/sole-female/", "count": 130227}, {"id": 90671, "type": "parody", "name": "original", "url": "/parody/original/", "count": 74352}, {"id": 130948, "type": "artist", "name": "sevengar", "url": "/artist/sevengar/", "count": 118}], "num_pages": 9, "num_favorites": 722}, {"id": 471559, "media_id": "2664193", "title": {"english": "[sand (Asahiru Yuu)] Kimi o Okashitai (Nier: Automata) [Chinese] [葱鱼个人汉化] [Digital]", "japanese": "[sand (浅ひるゆう)] キミヲ犯シタイ(ニーア オートマタ) [中国翻訳] [DL版]", "pretty": "Kimi o Okashitai"}, "images": {"pages": [{"t": "j", "w": 1280, "h": 1811}, {"t": "j", "w": 1280, "h": 1791}, {"t": "j", "w": 1280, "h": 1791}, {"t": "j", "w": 1280, "h": 1791}, {"t": "j", "w": 1280, "h": 1791}, {"t": "j", "w": 1280, "h": 1791}, {"t": "j", "w": 1280, "h": 1791}, {"t": "j", "w": 1280, "h": 1791}, {"t": "j", "w": 1280, "h": 1791}, {"t": "j", "w": 1280, "h": 1791}, {"t": "j", "w": 1280, "h": 1791}, {"t": "j", "w": 1280, "h": 1791}, {"t": "j", "w": 1280, "h": 1791}, {"t": "j", "w": 1280, "h": 1791}, {"t": "j", "w": 1280, "h": 1791}, {"t": "j", "w": 1280, "h": 1791}, {"t": "j", "w": 1280, "h": 1791}, {"t": "j", "w": 1280, "h": 1791}, {"t": "j", "w": 1280, "h": 1791}, {"t": "j", "w": 1280, "h": 1791}, {"t": "j", "w": 1280, "h": 1791}], "cover": {"t": "j", "w": 350, "h": 495}, "thumbnail": {"t": "j", "w": 250, "h": 354}}, "scanlator": "", "upload_date": 1693825576, "tags": [{"id": 2937, "type": "tag", "name": "big breasts", "url": "/tag/big-breasts/", "count": 159887}, {"id": 17249, "type": "language", "name": "translated", "url": "/language/translated/", "count": 195366}, {"id": 25614, "type": "tag", "name": "paizuri", "url": "/tag/paizuri/", "count": 33098}, {"id": 29506, "type": "group", "name": "sand", "url": "/group/sand/", "count": 64}, {"id": 29963, "type": "language", "name": "chinese", "url": "/language/chinese/", "count": 97324}, {"id": 31012, "type": "tag", "name": "blindfold", "url": "/tag/blindfold/", "count": 8419}, {"id": 33172, "type": "category", "name": "doujinshi", "url": "/category/doujinshi/", "count": 356214}, {"id": 35762, "type": "tag", "name": "sole female", "url": "/tag/sole-female/", "count": 131264}, {"id": 35763, "type": "tag", "name": "sole male", "url": "/tag/sole-male/", "count": 116602}, {"id": 71544, "type": "character", "name": "2b", "url": "/character/2b/", "count": 150}, {"id": 73370, "type": "parody", "name": "nier automata", "url": "/parody/nier-automata/", "count": 157}, {"id": 78281, "type": "character", "name": "9s", "url": "/character/9s/", "count": 95}, {"id": 103103, "type": "artist", "name": "asahiru yuu", "url": "/artist/asahiru-yuu/", "count": 63}], "num_pages": 21, "num_favorites": 2002}, {"id": 471558, "media_id": "2664192", "title": {"english": "(C102) [Ikihaji Hummingbird (Amano Don)] Gals Showdown (Goddess of Victory: Nikke) [Chinese] [葱鱼个人汉化]", "japanese": "(C102) [生き恥ハミングバード (天野どん)] Gals Showdown (勝利の女神:NIKKE) [中国翻訳]", "pretty": "Gals Showdown"}, "images": {"pages": [{"t": "j", "w": 1280, "h": 1780}, {"t": "j", "w": 1280, "h": 1866}, {"t": "j", "w": 1280, "h": 1844}, {"t": "j", "w": 1280, "h": 1844}, {"t": "j", "w": 1280, "h": 1844}, {"t": "j", "w": 1280, "h": 1844}, {"t": "j", "w": 1280, "h": 1844}, {"t": "j", "w": 1280, "h": 1844}, {"t": "j", "w": 1280, "h": 1844}, {"t": "j", "w": 1280, "h": 1844}, {"t": "j", "w": 1280, "h": 1844}, {"t": "j", "w": 1280, "h": 1844}, {"t": "j", "w": 1280, "h": 1844}, {"t": "j", "w": 1280, "h": 1844}, {"t": "j", "w": 1280, "h": 1844}, {"t": "j", "w": 1280, "h": 1844}, {"t": "j", "w": 1280, "h": 1844}, {"t": "j", "w": 1280, "h": 1844}, {"t": "j", "w": 1280, "h": 1844}, {"t": "j", "w": 1280, "h": 1844}, {"t": "j", "w": 1280, "h": 1844}, {"t": "j", "w": 1280, "h": 1844}, {"t": "j", "w": 1280, "h": 1844}, {"t": "j", "w": 1280, "h": 1844}, {"t": "j", "w": 1280, "h": 1844}, {"t": "j", "w": 1280, "h": 1844}, {"t": "j", "w": 1280, "h": 1844}, {"t": "j", "w": 1280, "h": 1844}, {"t": "j", "w": 1280, "h": 1844}, {"t": "j", "w": 1280, "h": 1844}, {"t": "j", "w": 1280, "h": 1844}, {"t": "j", "w": 1280, "h": 1844}, {"t": "j", "w": 1280, "h": 1844}, {"t": "j", "w": 1280, "h": 1818}, {"t": "j", "w": 1280, "h": 1957}, {"t": "j", "w": 1080, "h": 1991}, {"t": "j", "w": 1280, "h": 905}, {"t": "j", "w": 1243, "h": 2864}, {"t": "j", "w": 1280, "h": 1810}, {"t": "j", "w": 1076, "h": 2456}, {"t": "j", "w": 1080, "h": 2046}, {"t": "j", "w": 842, "h": 1636}, {"t": "j", "w": 1280, "h": 1908}, {"t": "j", "w": 1252, "h": 2436}, {"t": "j", "w": 1200, "h": 1698}, {"t": "j", "w": 1280, "h": 2260}], "cover": {"t": "j", "w": 350, "h": 486}, "thumbnail": {"t": "j", "w": 250, "h": 348}}, "scanlator": "", "upload_date": 1693825393, "tags": [{"id": 2937, "type": "tag", "name": "big breasts", "url": "/tag/big-breasts/", "count": 158739}, {"id": 8010, "type": "tag", "name": "group", "url": "/tag/group/", "count": 99763}, {"id": 15348, "type": "tag", "name": "ffm threesome", "url": "/tag/ffm-threesome/", "count": 27518}, {"id": 17249, "type": "language", "name": "translated", "url": "/language/translated/", "count": 193884}, {"id": 24380, "type": "tag", "name": "pantyhose", "url": "/tag/pantyhose/", "count": 21113}, {"id": 25050, "type": "tag", "name": "gyaru", "url": "/tag/gyaru/", "count": 6902}, {"id": 29859, "type": "tag", "name": "blowjob", "url": "/tag/blowjob/", "count": 67906}, {"id": 29963, "type": "language", "name": "chinese", "url": "/language/chinese/", "count": 96317}, {"id": 31044, "type": "tag", "name": "collar", "url": "/tag/collar/", "count": 23224}, {"id": 33172, "type": "category", "name": "doujinshi", "url": "/category/doujinshi/", "count": 354212}, {"id": 35763, "type": "tag", "name": "sole male", "url": "/tag/sole-male/", "count": 115578}, {"id": 49959, "type": "artist", "name": "nodame", "url": "/artist/nodame/", "count": 53}, {"id": 81707, "type": "tag", "name": "beauty mark", "url": "/tag/beauty-mark/", "count": 10449}, {"id": 92923, "type": "character", "name": "shikikan", "url": "/character/shikikan/", "count": 905}, {"id": 93324, "type": "tag", "name": "fishnets", "url": "/tag/fishnets/", "count": 1591}, {"id": 109785, "type": "group", "name": "ikihaji hummingbird", "url": "/group/ikihaji-hummingbird/", "count": 40}, {"id": 122908, "type": "tag", "name": "very long hair", "url": "/tag/very-long-hair/", "count": 4541}, {"id": 144055, "type": "parody", "name": "goddess of victory nikke", "url": "/parody/goddess-of-victory-nikke/", "count": 92}, {"id": 145394, "type": "character", "name": "rupee", "url": "/character/rupee/", "count": 7}, {"id": 147273, "type": "character", "name": "viper", "url": "/character/viper/", "count": 8}], "num_pages": 46, "num_favorites": 3093}, {"id": 471557, "media_id": "2664191", "title": {"english": "(C102) [Ink Complex (Tomohiro Kai)] Lost 2 Hours (Goddess of Victory:Nikke) [Chinese] [葱鱼个人汉化]", "japanese": "(C102) [Ink Complex (智弘カイ)] Lost 2 Hours (勝利の女神:NIKKE) [中国翻訳]", "pretty": "Lost 2 Hours"}, "images": {"pages": [{"t": "j", "w": 1280, "h": 1780}, {"t": "j", "w": 1280, "h": 1779}, {"t": "j", "w": 1280, "h": 1841}, {"t": "j", "w": 1280, "h": 1841}, {"t": "j", "w": 1280, "h": 1841}, {"t": "j", "w": 1280, "h": 1841}, {"t": "j", "w": 1280, "h": 1841}, {"t": "j", "w": 1280, "h": 1841}, {"t": "j", "w": 1280, "h": 1841}, {"t": "j", "w": 1280, "h": 1841}, {"t": "j", "w": 1280, "h": 1841}, {"t": "j", "w": 1280, "h": 1841}, {"t": "j", "w": 1280, "h": 1841}, {"t": "j", "w": 1280, "h": 1841}, {"t": "j", "w": 1280, "h": 1841}, {"t": "j", "w": 1280, "h": 1841}, {"t": "j", "w": 1280, "h": 1841}, {"t": "j", "w": 1280, "h": 1841}, {"t": "j", "w": 1280, "h": 1841}, {"t": "j", "w": 1280, "h": 1841}, {"t": "j", "w": 1280, "h": 1841}, {"t": "j", "w": 1280, "h": 1841}, {"t": "j", "w": 1280, "h": 1841}, {"t": "j", "w": 1280, "h": 1841}, {"t": "j", "w": 1280, "h": 1841}, {"t": "j", "w": 1280, "h": 1841}, {"t": "j", "w": 1280, "h": 1841}, {"t": "j", "w": 1280, "h": 1841}, {"t": "j", "w": 1280, "h": 1841}, {"t": "j", "w": 1280, "h": 1841}, {"t": "j", "w": 1280, "h": 1819}], "cover": {"t": "j", "w": 350, "h": 486}, "thumbnail": {"t": "j", "w": 250, "h": 348}}, "scanlator": "", "upload_date": 1693825060, "tags": [{"id": 2937, "type": "tag", "name": "big breasts", "url": "/tag/big-breasts/", "count": 159523}, {"id": 17249, "type": "language", "name": "translated", "url": "/language/translated/", "count": 194895}, {"id": 19528, "type": "group", "name": "ink complex", "url": "/group/ink-complex/", "count": 58}, {"id": 25614, "type": "tag", "name": "paizuri", "url": "/tag/paizuri/", "count": 33039}, {"id": 28371, "type": "artist", "name": "tomohiro kai", "url": "/artist/tomohiro-kai/", "count": 95}, {"id": 29963, "type": "language", "name": "chinese", "url": "/language/chinese/", "count": 97013}, {"id": 33172, "type": "category", "name": "doujinshi", "url": "/category/doujinshi/", "count": 355630}, {"id": 35762, "type": "tag", "name": "sole female", "url": "/tag/sole-female/", "count": 130892}, {"id": 35763, "type": "tag", "name": "sole male", "url": "/tag/sole-male/", "count": 116263}, {"id": 76598, "type": "character", "name": "mary", "url": "/character/mary/", "count": 22}, {"id": 92923, "type": "character", "name": "shikikan", "url": "/character/shikikan/", "count": 911}, {"id": 144055, "type": "parody", "name": "goddess of victory nikke", "url": "/parody/goddess-of-victory-nikke/", "count": 93}], "num_pages": 31, "num_favorites": 3679}, {"id": 471556, "media_id": "2664186", "title": {"english": "[Hiki Yuichi] Oujitachi no Insan | 王子们的淫餐 [Chinese] [看海汉化组] [Digital]", "japanese": "[樋木ゆいち] 王子達の淫餐 [中国翻訳] [DL版]", "pretty": "Oujitachi no Insan | 王子们的淫餐"}, "images": {"pages": [{"t": "j", "w": 800, "h": 1138}, {"t": "j", "w": 800, "h": 1138}, {"t": "j", "w": 800, "h": 1138}, {"t": "j", "w": 800, "h": 1138}, {"t": "j", "w": 800, "h": 1138}, {"t": "j", "w": 800, "h": 1138}, {"t": "j", "w": 800, "h": 1138}, {"t": "j", "w": 800, "h": 1138}, {"t": "j", "w": 800, "h": 1138}, {"t": "j", "w": 800, "h": 1138}, {"t": "j", "w": 800, "h": 1138}, {"t": "j", "w": 800, "h": 1138}, {"t": "j", "w": 800, "h": 1138}, {"t": "j", "w": 800, "h": 1138}, {"t": "j", "w": 800, "h": 1138}, {"t": "j", "w": 800, "h": 1138}, {"t": "j", "w": 800, "h": 1138}, {"t": "j", "w": 800, "h": 1138}, {"t": "j", "w": 800, "h": 1138}, {"t": "j", "w": 800, "h": 1138}, {"t": "j", "w": 800, "h": 1138}, {"t": "j", "w": 800, "h": 1138}, {"t": "j", "w": 800, "h": 1138}, {"t": "j", "w": 800, "h": 1138}, {"t": "j", "w": 800, "h": 1138}, {"t": "j", "w": 800, "h": 1138}, {"t": "j", "w": 800, "h": 1138}, {"t": "j", "w": 800, "h": 1138}, {"t": "j", "w": 800, "h": 1138}, {"t": "j", "w": 800, "h": 1138}, {"t": "j", "w": 774, "h": 600}, {"t": "j", "w": 800, "h": 1138}, {"t": "j", "w": 800, "h": 1138}, {"t": "j", "w": 800, "h": 1138}, {"t": "j", "w": 800, "h": 1138}, {"t": "j", "w": 800, "h": 1138}, {"t": "j", "w": 800, "h": 1138}, {"t": "j", "w": 800, "h": 1138}, {"t": "j", "w": 800, "h": 1138}, {"t": "j", "w": 800, "h": 1138}, {"t": "j", "w": 800, "h": 1138}, {"t": "j", "w": 800, "h": 1138}, {"t": "j", "w": 800, "h": 1138}, {"t": "j", "w": 800, "h": 1138}, {"t": "j", "w": 800, "h": 1138}, {"t": "j", "w": 800, "h": 1138}, {"t": "j", "w": 800, "h": 1138}, {"t": "j", "w": 800, "h": 1138}, {"t": "j", "w": 800, "h": 1138}, {"t": "j", "w": 800, "h": 1138}, {"t": "j", "w": 800, "h": 1138}, {"t": "j", "w": 800, "h": 1138}, {"t": "j", "w": 800, "h": 1138}, {"t": "j", "w": 800, "h": 1138}, {"t": "j", "w": 800, "h": 1138}, {"t": "j", "w": 800, "h": 1138}, {"t": "j", "w": 800, "h": 1138}, {"t": "j", "w": 800, "h": 1138}, {"t": "j", "w": 800, "h": 1138}, {"t": "j", "w": 800, "h": 1138}, {"t": "j", "w": 800, "h": 1138}, {"t": "j", "w": 800, "h": 1138}, {"t": "j", "w": 800, "h": 1138}, {"t": "j", "w": 800, "h": 1138}, {"t": "j", "w": 800, "h": 1138}, {"t": "j", "w": 800, "h": 1138}, {"t": "j", "w": 800, "h": 1137}, {"t": "j", "w": 800, "h": 1138}, {"t": "j", "w": 800, "h": 1138}, {"t": "j", "w": 800, "h": 1138}, {"t": "j", "w": 800, "h": 1138}, {"t": "j", "w": 774, "h": 600}, {"t": "j", "w": 800, "h": 1138}, {"t": "j", "w": 800, "h": 1138}, {"t": "j", "w": 800, "h": 1138}, {"t": "j", "w": 800, "h": 1138}, {"t": "j", "w": 800, "h": 1138}, {"t": "j", "w": 800, "h": 1138}, {"t": "j", "w": 800, "h": 1138}, {"t": "j", "w": 800, "h": 1138}, {"t": "j", "w": 800, "h": 1138}, {"t": "j", "w": 800, "h": 1138}, {"t": "j", "w": 800, "h": 1138}, {"t": "j", "w": 800, "h": 1138}, {"t": "j", "w": 800, "h": 1138}, {"t": "j", "w": 800, "h": 1138}, {"t": "j", "w": 800, "h": 1138}, {"t": "j", "w": 800, "h": 1138}, {"t": "j", "w": 800, "h": 1137}, {"t": "j", "w": 800, "h": 1138}, {"t": "j", "w": 800, "h": 1138}, {"t": "j", "w": 800, "h": 1138}, {"t": "j", "w": 800, "h": 1138}, {"t": "j", "w": 800, "h": 1138}, {"t": "j", "w": 800, "h": 1138}, {"t": "j", "w": 800, "h": 1138}, {"t": "j", "w": 800, "h": 1138}, {"t": "j", "w": 800, "h": 1138}, {"t": "j", "w": 800, "h": 1138}, {"t": "j", "w": 800, "h": 1138}, {"t": "j", "w": 800, "h": 1138}, {"t": "j", "w": 800, "h": 1138}, {"t": "j", "w": 800, "h": 1138}, {"t": "j", "w": 800, "h": 1138}, {"t": "j", "w": 800, "h": 1138}, {"t": "j", "w": 800, "h": 1138}, {"t": "j", "w": 800, "h": 1138}, {"t": "j", "w": 800, "h": 1138}, {"t": "j", "w": 800, "h": 1138}, {"t": "j", "w": 800, "h": 1138}, {"t": "j", "w": 800, "h": 1138}, {"t": "j", "w": 800, "h": 1138}, {"t": "j", "w": 800, "h": 1138}, {"t": "j", "w": 800, "h": 1138}, {"t": "j", "w": 800, "h": 1138}, {"t": "j", "w": 800, "h": 1138}, {"t": "j", "w": 800, "h": 1138}, {"t": "j", "w": 800, "h": 1138}, {"t": "j", "w": 700, "h": 840}, {"t": "j", "w": 800, "h": 1138}, {"t": "j", "w": 800, "h": 1138}, {"t": "j", "w": 800, "h": 1138}, {"t": "j", "w": 800, "h": 1138}, {"t": "j", "w": 800, "h": 1138}, {"t": "j", "w": 800, "h": 1138}, {"t": "j", "w": 800, "h": 1138}, {"t": "j", "w": 800, "h": 1138}, {"t": "j", "w": 800, "h": 1138}, {"t": "j", "w": 800, "h": 1138}, {"t": "j", "w": 800, "h": 1138}, {"t": "j", "w": 800, "h": 1138}, {"t": "j", "w": 800, "h": 1138}, {"t": "j", "w": 800, "h": 1138}, {"t": "j", "w": 800, "h": 1138}, {"t": "j", "w": 800, "h": 1138}, {"t": "j", "w": 800, "h": 1138}, {"t": "j", "w": 800, "h": 1138}, {"t": "j", "w": 800, "h": 1138}, {"t": "j", "w": 800, "h": 1138}, {"t": "j", "w": 800, "h": 1138}, {"t": "j", "w": 800, "h": 1138}, {"t": "j", "w": 800, "h": 1138}, {"t": "j", "w": 800, "h": 1138}, {"t": "j", "w": 800, "h": 1138}, {"t": "j", "w": 800, "h": 1138}, {"t": "j", "w": 800, "h": 1138}, {"t": "j", "w": 800, "h": 1138}, {"t": "j", "w": 800, "h": 1138}, {"t": "j", "w": 800, "h": 1138}, {"t": "j", "w": 800, "h": 1138}, {"t": "j", "w": 800, "h": 1138}, {"t": "j", "w": 800, "h": 1138}, {"t": "j", "w": 800, "h": 1138}, {"t": "j", "w": 800, "h": 1138}, {"t": "j", "w": 800, "h": 1138}, {"t": "j", "w": 800, "h": 1138}, {"t": "j", "w": 800, "h": 1138}, {"t": "j", "w": 800, "h": 1138}, {"t": "j", "w": 800, "h": 1137}, {"t": "j", "w": 700, "h": 840}, {"t": "j", "w": 800, "h": 1138}, {"t": "j", "w": 800, "h": 1138}, {"t": "j", "w": 800, "h": 1138}, {"t": "j", "w": 800, "h": 1138}, {"t": "j", "w": 800, "h": 1138}, {"t": "j", "w": 800, "h": 1138}, {"t": "j", "w": 800, "h": 1138}, {"t": "j", "w": 800, "h": 1138}, {"t": "j", "w": 800, "h": 1138}, {"t": "j", "w": 800, "h": 1138}, {"t": "j", "w": 800, "h": 1138}, {"t": "j", "w": 800, "h": 1138}, {"t": "j", "w": 800, "h": 1138}, {"t": "j", "w": 800, "h": 1138}, {"t": "j", "w": 800, "h": 1138}, {"t": "j", "w": 800, "h": 1138}, {"t": "j", "w": 800, "h": 1138}, {"t": "j", "w": 800, "h": 1138}, {"t": "j", "w": 800, "h": 1138}, {"t": "j", "w": 800, "h": 1138}, {"t": "j", "w": 800, "h": 1138}, {"t": "j", "w": 800, "h": 1138}, {"t": "j", "w": 800, "h": 1138}, {"t": "j", "w": 800, "h": 1138}, {"t": "j", "w": 800, "h": 1138}, {"t": "j", "w": 800, "h": 1138}, {"t": "j", "w": 800, "h": 1138}, {"t": "j", "w": 800, "h": 1138}, {"t": "j", "w": 800, "h": 1138}, {"t": "j", "w": 800, "h": 1138}, {"t": "j", "w": 800, "h": 1138}, {"t": "j", "w": 800, "h": 1138}, {"t": "j", "w": 800, "h": 1138}, {"t": "j", "w": 800, "h": 1138}, {"t": "j", "w": 800, "h": 1138}, {"t": "j", "w": 800, "h": 1138}, {"t": "j", "w": 800, "h": 1138}, {"t": "j", "w": 800, "h": 1138}, {"t": "j", "w": 800, "h": 1138}, {"t": "j", "w": 800, "h": 1138}, {"t": "j", "w": 800, "h": 1138}, {"t": "j", "w": 800, "h": 1138}, {"t": "j", "w": 700, "h": 840}, {"t": "j", "w": 800, "h": 1138}, {"t": "j", "w": 800, "h": 1138}, {"t": "j", "w": 800, "h": 1138}, {"t": "j", "w": 800, "h": 1138}, {"t": "j", "w": 800, "h": 1138}, {"t": "j", "w": 800, "h": 1138}, {"t": "j", "w": 800, "h": 1138}, {"t": "j", "w": 800, "h": 1138}, {"t": "j", "w": 800, "h": 1138}, {"t": "j", "w": 800, "h": 1138}, {"t": "j", "w": 800, "h": 1138}, {"t": "j", "w": 800, "h": 1138}, {"t": "j", "w": 800, "h": 1138}, {"t": "j", "w": 800, "h": 1138}, {"t": "j", "w": 800, "h": 1138}, {"t": "j", "w": 800, "h": 1138}, {"t": "j", "w": 800, "h": 1138}, {"t": "j", "w": 800, "h": 1138}, {"t": "j", "w": 800, "h": 1138}, {"t": "j", "w": 800, "h": 1138}, {"t": "j", "w": 800, "h": 1138}, {"t": "j", "w": 800, "h": 1138}, {"t": "j", "w": 800, "h": 1138}, {"t": "j", "w": 800, "h": 1138}, {"t": "j", "w": 800, "h": 1138}, {"t": "j", "w": 800, "h": 1138}, {"t": "j", "w": 800, "h": 1138}, {"t": "j", "w": 800, "h": 1138}, {"t": "j", "w": 800, "h": 1138}, {"t": "j", "w": 800, "h": 1138}, {"t": "j", "w": 800, "h": 1138}, {"t": "j", "w": 800, "h": 1138}, {"t": "j", "w": 800, "h": 1138}, {"t": "j", "w": 800, "h": 1138}, {"t": "j", "w": 800, "h": 1138}, {"t": "j", "w": 800, "h": 1138}, {"t": "j", "w": 800, "h": 1138}, {"t": "j", "w": 800, "h": 1138}, {"t": "j", "w": 800, "h": 1138}, {"t": "j", "w": 800, "h": 1138}, {"t": "j", "w": 700, "h": 840}, {"t": "j", "w": 800, "h": 1138}, {"t": "j", "w": 800, "h": 1138}, {"t": "j", "w": 800, "h": 1138}, {"t": "j", "w": 800, "h": 1138}, {"t": "j", "w": 800, "h": 1138}, {"t": "j", "w": 800, "h": 1138}, {"t": "j", "w": 800, "h": 1138}, {"t": "j", "w": 800, "h": 1138}, {"t": "j", "w": 800, "h": 1138}, {"t": "j", "w": 800, "h": 1138}, {"t": "j", "w": 800, "h": 1138}, {"t": "j", "w": 800, "h": 1138}, {"t": "j", "w": 800, "h": 1138}, {"t": "j", "w": 800, "h": 1138}, {"t": "j", "w": 800, "h": 1138}, {"t": "j", "w": 800, "h": 1138}, {"t": "j", "w": 800, "h": 1138}, {"t": "j", "w": 800, "h": 1138}, {"t": "j", "w": 800, "h": 1138}, {"t": "j", "w": 700, "h": 840}, {"t": "j", "w": 1280, "h": 1920}], "cover": {"t": "j", "w": 350, "h": 498}, "thumbnail": {"t": "j", "w": 250, "h": 356}}, "scanlator": "", "upload_date": 1693824821, "tags": [{"id": 17249, "type": "language", "name": "translated", "url": "/language/translated/", "count": 192895}, {"id": 21712, "type": "tag", "name": "males only", "url": "/tag/males-only/", "count": 39419}, {"id": 23237, "type": "tag", "name": "tankoubon", "url": "/tag/tankoubon/", "count": 32007}, {"id": 23895, "type": "tag", "name": "yaoi", "url": "/tag/yaoi/", "count": 46625}, {"id": 29963, "type": "language", "name": "chinese", "url": "/language/chinese/", "count": 95745}, {"id": 33173, "type": "category", "name": "manga", "url": "/category/manga/", "count": 112576}, {"id": 149540, "type": "artist", "name": "hiki yuichi", "url": "/artist/hiki-yuichi/", "count": 1}], "num_pages": 265, "num_favorites": 482}, {"id": 471555, "media_id": "2664185", "title": {"english": "(C100) [MAT (Pararan)] Okusuri no Jikan dayo ♥ | It's time for your medicine! ♥ (Nekomata Okayu) [English] [DKKMD Translations]", "japanese": "(C100) [MAT (ぱららん)] お薬の時間だよぉ♥ (猫又おかゆ) [英訳]", "pretty": "Okusuri no Jikan dayo ♥ | It's time for your medicine! ♥"}, "images": {"pages": [{"t": "j", "w": 1280, "h": 1792}, {"t": "j", "w": 1280, "h": 1787}, {"t": "j", "w": 1280, "h": 1862}, {"t": "j", "w": 1280, "h": 1853}, {"t": "j", "w": 1280, "h": 1826}, {"t": "j", "w": 1280, "h": 1849}, {"t": "j", "w": 1280, "h": 1842}, {"t": "j", "w": 1280, "h": 1823}, {"t": "j", "w": 1280, "h": 1837}, {"t": "j", "w": 1280, "h": 1828}, {"t": "j", "w": 1280, "h": 1835}, {"t": "j", "w": 1280, "h": 1832}, {"t": "j", "w": 1280, "h": 1859}, {"t": "j", "w": 1280, "h": 1834}, {"t": "j", "w": 1280, "h": 1833}, {"t": "j", "w": 1280, "h": 1835}, {"t": "j", "w": 1280, "h": 1852}, {"t": "j", "w": 1280, "h": 1823}, {"t": "j", "w": 1280, "h": 1834}, {"t": "j", "w": 1280, "h": 1834}, {"t": "j", "w": 1280, "h": 1838}, {"t": "j", "w": 1280, "h": 1827}, {"t": "j", "w": 1280, "h": 1819}, {"t": "j", "w": 1280, "h": 1833}, {"t": "j", "w": 1280, "h": 1844}, {"t": "j", "w": 1280, "h": 1826}, {"t": "j", "w": 1280, "h": 1831}, {"t": "j", "w": 1280, "h": 1856}, {"t": "j", "w": 1280, "h": 1837}, {"t": "j", "w": 1280, "h": 1827}, {"t": "j", "w": 1280, "h": 1841}, {"t": "j", "w": 1280, "h": 1830}, {"t": "j", "w": 1280, "h": 1919}, {"t": "j", "w": 1280, "h": 1914}, {"t": "j", "w": 1280, "h": 1839}], "cover": {"t": "j", "w": 350, "h": 490}, "thumbnail": {"t": "j", "w": 250, "h": 350}}, "scanlator": "", "upload_date": 1693823048, "tags": [{"id": 2937, "type": "tag", "name": "big breasts", "url": "/tag/big-breasts/", "count": 159535}, {"id": 6817, "type": "tag", "name": "unusual pupils", "url": "/tag/unusual-pupils/", "count": 13005}, {"id": 7256, "type": "tag", "name": "mmf threesome", "url": "/tag/mmf-threesome/", "count": 15502}, {"id": 12227, "type": "language", "name": "english", "url": "/language/english/", "count": 109476}, {"id": 13720, "type": "tag", "name": "nakadashi", "url": "/tag/nakadashi/", "count": 75244}, {"id": 13989, "type": "tag", "name": "ahegao", "url": "/tag/ahegao/", "count": 43883}, {"id": 17249, "type": "language", "name": "translated", "url": "/language/translated/", "count": 194896}, {"id": 22079, "type": "tag", "name": "drugs", "url": "/tag/drugs/", "count": 9988}, {"id": 25614, "type": "tag", "name": "paizuri", "url": "/tag/paizuri/", "count": 33044}, {"id": 31044, "type": "tag", "name": "collar", "url": "/tag/collar/", "count": 23356}, {"id": 31386, "type": "tag", "name": "catgirl", "url": "/tag/catgirl/", "count": 10780}, {"id": 33172, "type": "category", "name": "doujinshi", "url": "/category/doujinshi/", "count": 355630}, {"id": 35762, "type": "tag", "name": "sole female", "url": "/tag/sole-female/", "count": 130906}, {"id": 70892, "type": "artist", "name": "pararan", "url": "/artist/pararan/", "count": 19}, {"id": 81774, "type": "tag", "name": "kemonomimi", "url": "/tag/kemonomimi/", "count": 16829}, {"id": 104227, "type": "tag", "name": "tail", "url": "/tag/tail/", "count": 7439}, {"id": 104893, "type": "tag", "name": "vtuber", "url": "/tag/vtuber/", "count": 2038}, {"id": 127065, "type": "parody", "name": "hololive", "url": "/parody/hololive/", "count": 934}, {"id": 128277, "type": "character", "name": "nekomata okayu", "url": "/character/nekomata-okayu/", "count": 79}], "num_pages": 35, "num_favorites": 2781}, {"id": 471554, "media_id": "2664183", "title": {"english": "[Azumaya Manju] \"Okusan no Ana, Ore no de Fusai de Agemasu ne?\" Yokkyuu Fuman na Hitozuma ga Rinjin Ryuugakusei no XL Chinpo ni Ochiru made... [Full Color] 3", "japanese": "[あずまやまんぢゅう] 「奥さんの穴、俺ので塞いであげますね？」欲求不満な人妻が隣人留学生のXLち〇ぽに堕ちるまで…【フルカラー】 （3）", "pretty": "\"Okusan no Ana, Ore no de Fusai de Agemasu ne?\" Yokkyuu Fuman na Hitozuma ga Rinjin Ryuugakusei no XL Chinpo ni Ochiru made...3"}, "images": {"pages": [{"t": "j", "w": 1057, "h": 1500}, {"t": "j", "w": 1057, "h": 1500}, {"t": "j", "w": 1057, "h": 1500}, {"t": "j", "w": 1057, "h": 1500}, {"t": "j", "w": 1057, "h": 1500}, {"t": "j", "w": 1057, "h": 1500}, {"t": "j", "w": 1057, "h": 1500}, {"t": "j", "w": 1057, "h": 1500}, {"t": "j", "w": 1057, "h": 1500}, {"t": "j", "w": 1057, "h": 1500}, {"t": "j", "w": 1057, "h": 1500}, {"t": "j", "w": 1057, "h": 1500}, {"t": "j", "w": 1057, "h": 1500}, {"t": "j", "w": 1057, "h": 1500}, {"t": "j", "w": 1057, "h": 1500}, {"t": "j", "w": 1057, "h": 1500}, {"t": "j", "w": 1057, "h": 1500}, {"t": "j", "w": 1057, "h": 1500}, {"t": "j", "w": 1057, "h": 1500}, {"t": "j", "w": 1057, "h": 1500}, {"t": "j", "w": 1057, "h": 1500}, {"t": "j", "w": 1057, "h": 1500}, {"t": "j", "w": 1057, "h": 1500}, {"t": "j", "w": 1057, "h": 1500}, {"t": "j", "w": 1057, "h": 1500}, {"t": "j", "w": 1057, "h": 1500}, {"t": "j", "w": 1057, "h": 1500}, {"t": "j", "w": 1057, "h": 1500}], "cover": {"t": "j", "w": 350, "h": 496}, "thumbnail": {"t": "j", "w": 250, "h": 355}}, "scanlator": "", "upload_date": 1693822784, "tags": [{"id": 6346, "type": "language", "name": "japanese", "url": "/language/japanese/", "count": 262057}, {"id": 8368, "type": "tag", "name": "full censorship", "url": "/tag/full-censorship/", "count": 26439}, {"id": 9260, "type": "tag", "name": "cheating", "url": "/tag/cheating/", "count": 20977}, {"id": 20905, "type": "tag", "name": "full color", "url": "/tag/full-color/", "count": 59172}, {"id": 21572, "type": "tag", "name": "multi-work series", "url": "/tag/multi-work-series/", "count": 32893}, {"id": 33173, "type": "category", "name": "manga", "url": "/category/manga/", "count": 112724}, {"id": 35762, "type": "tag", "name": "sole female", "url": "/tag/sole-female/", "count": 129617}, {"id": 35763, "type": "tag", "name": "sole male", "url": "/tag/sole-male/", "count": 115094}, {"id": 139794, "type": "artist", "name": "azumaya manju", "url": "/artist/azumaya-manju/", "count": 19}], "num_pages": 28, "num_favorites": 387}, {"id": "471553", "media_id": "2664182", "title": {"english": "[Uko] Ron't touch me!! (Namaiki Love Hole) [Chinese] [白杨汉化组] [Digital]", "japanese": "[うこ] Ron't touch me!! (生イキらぶほーる) [中国翻訳] [DL版]", "pretty": "Ron't touch me!!"}, "images": {"pages": [{"t": "j", "w": 1057, "h": 1500}, {"t": "j", "w": 1057, "h": 1500}, {"t": "j", "w": 1057, "h": 1500}, {"t": "j", "w": 1057, "h": 1500}, {"t": "j", "w": 1057, "h": 1500}, {"t": "j", "w": 1057, "h": 1500}, {"t": "j", "w": 1057, "h": 1500}, {"t": "j", "w": 1057, "h": 1500}, {"t": "j", "w": 1057, "h": 1500}, {"t": "j", "w": 1057, "h": 1500}, {"t": "j", "w": 1057, "h": 1500}, {"t": "j", "w": 1057, "h": 1500}, {"t": "j", "w": 1057, "h": 1500}, {"t": "j", "w": 1057, "h": 1500}, {"t": "j", "w": 1057, "h": 1500}, {"t": "j", "w": 1057, "h": 1500}, {"t": "j", "w": 1057, "h": 1500}, {"t": "j", "w": 1057, "h": 1500}, {"t": "j", "w": 1057, "h": 1500}, {"t": "j", "w": 1057, "h": 1500}, {"t": "j", "w": 1057, "h": 1500}, {"t": "j", "w": 1057, "h": 1500}, {"t": "j", "w": 1057, "h": 1500}, {"t": "j", "w": 1057, "h": 1500}, {"t": "j", "w": 1057, "h": 1500}, {"t": "j", "w": 1057, "h": 1500}, {"t": "j", "w": 1057, "h": 1500}, {"t": "j", "w": 1057, "h": 1500}, {"t": "j", "w": 1057, "h": 1500}, {"t": "j", "w": 1057, "h": 1500}, {"t": "j", "w": 1057, "h": 1500}, {"t": "j", "w": 888, "h": 1219}, {"t": "j", "w": 1280, "h": 2049}], "cover": {"t": "j", "w": 350, "h": 496}, "thumbnail": {"t": "j", "w": 250, "h": 355}}, "scanlator": "", "upload_date": 1693822572, "tags": [{"id": 7752, "type": "tag", "name": "schoolboy uniform", "url": "/tag/schoolboy-uniform/", "count": 16855}, {"id": 10314, "type": "tag", "name": "schoolgirl uniform", "url": "/tag/schoolgirl-uniform/", "count": 75317}, {"id": 11941, "type": "tag", "name": "replaced", "url": "/tag/replaced/", "count": 4388}, {"id": 13720, "type": "tag", "name": "nakadashi", "url": "/tag/nakadashi/", "count": 75247}, {"id": 17249, "type": "language", "name": "translated", "url": "/language/translated/", "count": 194895}, {"id": 24201, "type": "tag", "name": "stockings", "url": "/tag/stockings/", "count": 92073}, {"id": 29859, "type": "tag", "name": "blowjob", "url": "/tag/blowjob/", "count": 68309}, {"id": 29963, "type": "language", "name": "chinese", "url": "/language/chinese/", "count": 97012}, {"id": 32996, "type": "tag", "name": "deepthroat", "url": "/tag/deepthroat/", "count": 5373}, {"id": 33173, "type": "category", "name": "manga", "url": "/category/manga/", "count": 113482}, {"id": 35762, "type": "tag", "name": "sole female", "url": "/tag/sole-female/", "count": 130910}, {"id": 35763, "type": "tag", "name": "sole male", "url": "/tag/sole-male/", "count": 116277}, {"id": 80888, "type": "artist", "name": "uko", "url": "/artist/uko/", "count": 46}, {"id": 85295, "type": "tag", "name": "twintails", "url": "/tag/twintails/", "count": 23931}], "num_pages": 33, "num_favorites": 1688}, {"id": 471552, "media_id": "2664169", "title": {"english": "(C86) [Nagomiyasan (Suzuki Nago)] Shiori-chan, Yamaidon After School (Date A Live) [Chinese] [azertymango]", "japanese": "(C86) [なごみやさん (鈴木和)] 士織ちゃん、八舞丼アフタースクール (デート・ア・ライブ) [中国翻訳]", "pretty": "Shiori-chan, Yamaidon After School"}, "images": {"pages": [{"t": "j", "w": 1280, "h": 1820}, {"t": "j", "w": 1280, "h": 1820}, {"t": "j", "w": 1280, "h": 1818}, {"t": "j", "w": 1280, "h": 1822}, {"t": "j", "w": 1280, "h": 1822}, {"t": "j", "w": 1280, "h": 1822}, {"t": "j", "w": 1280, "h": 1822}, {"t": "j", "w": 1280, "h": 1822}, {"t": "j", "w": 1280, "h": 1822}, {"t": "j", "w": 1280, "h": 1825}, {"t": "j", "w": 1280, "h": 1825}, {"t": "j", "w": 1280, "h": 1824}, {"t": "j", "w": 1280, "h": 1824}, {"t": "j", "w": 1280, "h": 1825}, {"t": "j", "w": 1280, "h": 1825}, {"t": "j", "w": 1280, "h": 1825}, {"t": "j", "w": 1280, "h": 1825}, {"t": "j", "w": 1280, "h": 1825}, {"t": "j", "w": 1280, "h": 1825}, {"t": "j", "w": 1280, "h": 1825}, {"t": "j", "w": 1280, "h": 1825}, {"t": "j", "w": 1280, "h": 1825}, {"t": "j", "w": 1080, "h": 1614}], "cover": {"t": "j", "w": 350, "h": 498}, "thumbnail": {"t": "j", "w": 250, "h": 356}}, "scanlator": "", "upload_date": 1693822324, "tags": [{"id": 560, "type": "tag", "name": "twins", "url": "/tag/twins/", "count": 2439}, {"id": 4640, "type": "parody", "name": "date a live", "url": "/parody/date-a-live/", "count": 95}, {"id": 5916, "type": "character", "name": "yuzuru yamai", "url": "/character/yuzuru-yamai/", "count": 12}, {"id": 8010, "type": "tag", "name": "group", "url": "/tag/group/", "count": 100062}, {"id": 8368, "type": "tag", "name": "full censorship", "url": "/tag/full-censorship/", "count": 26673}, {"id": 10314, "type": "tag", "name": "schoolgirl uniform", "url": "/tag/schoolgirl-uniform/", "count": 75317}, {"id": 15348, "type": "tag", "name": "ffm threesome", "url": "/tag/ffm-threesome/", "count": 27642}, {"id": 15408, "type": "tag", "name": "femdom", "url": "/tag/femdom/", "count": 25724}, {"id": 15455, "type": "artist", "name": "suzuki nago", "url": "/artist/suzuki-nago/", "count": 76}, {"id": 15782, "type": "tag", "name": "crossdressing", "url": "/tag/crossdressing/", "count": 18431}, {"id": 16505, "type": "character", "name": "shido itsuka", "url": "/character/shido-itsuka/", "count": 53}, {"id": 17249, "type": "language", "name": "translated", "url": "/language/translated/", "count": 194895}, {"id": 19630, "type": "character", "name": "kaguya yamai", "url": "/character/kaguya-yamai/", "count": 12}, {"id": 22942, "type": "tag", "name": "incest", "url": "/tag/incest/", "count": 41144}, {"id": 29023, "type": "tag", "name": "tomgirl", "url": "/tag/tomgirl/", "count": 16365}, {"id": 29182, "type": "tag", "name": "blackmail", "url": "/tag/blackmail/", "count": 8312}, {"id": 29963, "type": "language", "name": "chinese", "url": "/language/chinese/", "count": 97012}, {"id": 31482, "type": "group", "name": "nagomiyasan", "url": "/group/nagomiyasan/", "count": 55}, {"id": 32341, "type": "tag", "name": "shotacon", "url": "/tag/shotacon/", "count": 54719}, {"id": 33172, "type": "category", "name": "doujinshi", "url": "/category/doujinshi/", "count": 355630}, {"id": 35763, "type": "tag", "name": "sole male", "url": "/tag/sole-male/", "count": 116277}, {"id": 36957, "type": "tag", "name": "bisexual", "url": "/tag/bisexual/", "count": 3159}, {"id": 114993, "type": "tag", "name": "shimaidon", "url": "/tag/shimaidon/", "count": 1131}], "num_pages": 23, "num_favorites": 343}, {"id": 471551, "media_id": "2664166", "title": {"english": "[habutton] GF came back from student trip (ongoing)", "japanese": "", "pretty": "GF came back from student trip"}, "images": {"pages": [{"t": "j", "w": 1280, "h": 1837}, {"t": "j", "w": 1280, "h": 1812}, {"t": "j", "w": 1280, "h": 1678}, {"t": "p", "w": 1045, "h": 1403}, {"t": "p", "w": 1045, "h": 1403}, {"t": "p", "w": 1045, "h": 1403}, {"t": "j", "w": 1280, "h": 1529}, {"t": "j", "w": 1280, "h": 1529}, {"t": "j", "w": 1280, "h": 1529}, {"t": "j", "w": 1280, "h": 1529}, {"t": "j", "w": 1280, "h": 1810}, {"t": "j", "w": 1280, "h": 1810}, {"t": "j", "w": 1280, "h": 1810}, {"t": "j", "w": 1280, "h": 1811}, {"t": "j", "w": 1280, "h": 1811}, {"t": "j", "w": 1280, "h": 1811}, {"t": "j", "w": 1280, "h": 1356}, {"t": "j", "w": 1280, "h": 1356}, {"t": "j", "w": 1280, "h": 1356}, {"t": "j", "w": 1280, "h": 1356}, {"t": "j", "w": 1280, "h": 1356}, {"t": "j", "w": 1280, "h": 1810}, {"t": "j", "w": 1280, "h": 1810}, {"t": "j", "w": 1280, "h": 1810}, {"t": "j", "w": 1280, "h": 1810}], "cover": {"t": "j", "w": 350, "h": 502}, "thumbnail": {"t": "j", "w": 250, "h": 359}}, "scanlator": "", "upload_date": 1693822139, "tags": [{"id": 1590, "type": "tag", "name": "sweating", "url": "/tag/sweating/", "count": 16140}, {"id": 2937, "type": "tag", "name": "big breasts", "url": "/tag/big-breasts/", "count": 159310}, {"id": 7142, "type": "tag", "name": "bbw", "url": "/tag/bbw/", "count": 7426}, {"id": 9083, "type": "tag", "name": "big ass", "url": "/tag/big-ass/", "count": 16632}, {"id": 12227, "type": "language", "name": "english", "url": "/language/english/", "count": 109380}, {"id": 16487, "type": "tag", "name": "weight gain", "url": "/tag/weight-gain/", "count": 378}, {"id": 33173, "type": "category", "name": "manga", "url": "/category/manga/", "count": 113353}, {"id": 127124, "type": "artist", "name": "habutton", "url": "/artist/habutton/", "count": 11}, {"id": 132893, "type": "tag", "name": "ssbbw", "url": "/tag/ssbbw/", "count": 70}], "num_pages": 25, "num_favorites": 354}, {"id": 471550, "media_id": "2664165", "title": {"english": "[Hachimiyatei (Hachimiya)] Onegai!! Shion-tan (Hololive) [Digital]", "japanese": "[八宮亭 (八宮)] おねがい!! シオンたん (ホロライブ) [DL版]", "pretty": "Onegai!! Shion-tan"}, "images": {"pages": [{"t": "j", "w": 1280, "h": 911}, {"t": "j", "w": 1280, "h": 1779}, {"t": "j", "w": 1280, "h": 1779}, {"t": "j", "w": 1280, "h": 1779}, {"t": "j", "w": 1280, "h": 1779}, {"t": "j", "w": 1280, "h": 1779}, {"t": "j", "w": 1280, "h": 1779}, {"t": "j", "w": 1280, "h": 1779}, {"t": "j", "w": 1280, "h": 1779}, {"t": "j", "w": 1280, "h": 1779}, {"t": "j", "w": 1280, "h": 1779}, {"t": "j", "w": 1280, "h": 1779}, {"t": "j", "w": 1280, "h": 1779}, {"t": "j", "w": 1280, "h": 1779}, {"t": "j", "w": 1280, "h": 1779}, {"t": "j", "w": 1280, "h": 1779}, {"t": "j", "w": 1280, "h": 1779}, {"t": "j", "w": 1280, "h": 1779}, {"t": "j", "w": 1280, "h": 1779}], "cover": {"t": "j", "w": 350, "h": 249}, "thumbnail": {"t": "j", "w": 250, "h": 178}}, "scanlator": "", "upload_date": 1693821946, "tags": [{"id": 2937, "type": "tag", "name": "big breasts", "url": "/tag/big-breasts/", "count": 159537}, {"id": 6346, "type": "language", "name": "japanese", "url": "/language/japanese/", "count": 263403}, {"id": 7546, "type": "tag", "name": "witch", "url": "/tag/witch/", "count": 1387}, {"id": 13720, "type": "tag", "name": "nakadashi", "url": "/tag/nakadashi/", "count": 75246}, {"id": 14283, "type": "tag", "name": "anal", "url": "/tag/anal/", "count": 95458}, {"id": 19018, "type": "tag", "name": "dark skin", "url": "/tag/dark-skin/", "count": 35303}, {"id": 19440, "type": "tag", "name": "lolicon", "url": "/tag/lolicon/", "count": 91961}, {"id": 20905, "type": "tag", "name": "full color", "url": "/tag/full-color/", "count": 59631}, {"id": 29859, "type": "tag", "name": "blowjob", "url": "/tag/blowjob/", "count": 68308}, {"id": 33172, "type": "category", "name": "doujinshi", "url": "/category/doujinshi/", "count": 355630}, {"id": 81774, "type": "tag", "name": "kemonomimi", "url": "/tag/kemonomimi/", "count": 16829}, {"id": 104893, "type": "tag", "name": "vtuber", "url": "/tag/vtuber/", "count": 2038}, {"id": 117206, "type": "character", "name": "murasaki shion", "url": "/character/murasaki-shion/", "count": 98}, {"id": 127065, "type": "parody", "name": "hololive", "url": "/parody/hololive/", "count": 934}, {"id": 142495, "type": "group", "name": "hachimiyatei", "url": "/group/hachimiyatei/", "count": 3}, {"id": 142496, "type": "artist", "name": "hachimiya", "url": "/artist/hachimiya/", "count": 3}, {"id": 144784, "type": "character", "name": "azki", "url": "/character/azki/", "count": 3}], "num_pages": 19, "num_favorites": 785}, {"id": 471549, "media_id": "2664160", "title": {"english": "[Ohara Makoto] InCha na Ore ga Madougu o Tsukatte Share House de Harem o Tsukutte Mita. Ch. 18", "japanese": "[おはら誠] 陰キャな俺が魔道具を使ってシェアハウスでハーレムをつくってみた。 18話", "pretty": "InCha na Ore ga Madougu o Tsukatte Share House de Harem o Tsukutte Mita. Ch. 18"}, "images": {"pages": [{"t": "j", "w": 1088, "h": 1563}, {"t": "j", "w": 1088, "h": 1563}, {"t": "j", "w": 1088, "h": 1563}, {"t": "j", "w": 1088, "h": 1563}, {"t": "j", "w": 1088, "h": 1563}, {"t": "j", "w": 1088, "h": 1563}, {"t": "j", "w": 1088, "h": 1563}, {"t": "j", "w": 1088, "h": 1563}, {"t": "j", "w": 1088, "h": 1563}, {"t": "j", "w": 1088, "h": 1563}, {"t": "j", "w": 1088, "h": 1563}, {"t": "j", "w": 1088, "h": 1563}, {"t": "j", "w": 1088, "h": 1563}, {"t": "j", "w": 1088, "h": 1563}, {"t": "j", "w": 1088, "h": 1563}, {"t": "j", "w": 1088, "h": 1563}, {"t": "j", "w": 1088, "h": 1563}, {"t": "j", "w": 1088, "h": 1563}, {"t": "j", "w": 1088, "h": 1563}, {"t": "j", "w": 1088, "h": 1563}], "cover": {"t": "j", "w": 350, "h": 503}, "thumbnail": {"t": "j", "w": 250, "h": 359}}, "scanlator": "", "upload_date": 1693821676, "tags": [{"id": 2937, "type": "tag", "name": "big breasts", "url": "/tag/big-breasts/", "count": 159431}, {"id": 6343, "type": "tag", "name": "pregnant", "url": "/tag/pregnant/", "count": 13851}, {"id": 6346, "type": "language", "name": "japanese", "url": "/language/japanese/", "count": 263297}, {"id": 8010, "type": "tag", "name": "group", "url": "/tag/group/", "count": 100015}, {"id": 8368, "type": "tag", "name": "full censorship", "url": "/tag/full-censorship/", "count": 26657}, {"id": 21572, "type": "tag", "name": "multi-work series", "url": "/tag/multi-work-series/", "count": 33303}, {"id": 24102, "type": "tag", "name": "lactation", "url": "/tag/lactation/", "count": 17191}, {"id": 33173, "type": "category", "name": "manga", "url": "/category/manga/", "count": 113423}, {"id": 106448, "type": "artist", "name": "ohara makoto", "url": "/artist/ohara-makoto/", "count": 59}], "num_pages": 20, "num_favorites": 526}], "num_pages": 19504, "per_page": 25}